Workbook

Sheet Léeme
A1: Inventario-Fotosíntesis · SOT Limpia
A2: Fuente única de verdad del inventario para la app Fotosíntesis. Generada consolidando
A3: Legacy + Convex + ModeloPrecios + Caja + Ventas + Kardex (reconciliación Sintesis).
A5: PESTAÑAS
A6: • Inventario — 1 fila por ítem (A–AP = esquema canónico de la app; AQ–AU = ayudas).
A7: • Lotes — catálogo de lotes (incluye 31 recuperados). mostrarComoLote=Sí → se vende como 1 card.
A8: • Sublotes — grupos curados de ítems que se venden juntos (subconjunto de un lote).
A9: • Proveedores / Clientes / Ventas — catálogos y transacciones.
A10: • Calidades — lista canónica + factor de precio (referencia).
A11: • Listas — fuente de los menús desplegables (no borrar).
A13: COLUMNAS CLAVE
A14: • Peso (ct) D — quilates (numérico). Peso (gr) AQ — gramos de joya (numérico).
... A30: • Ver columna 'Notas / conflictos' por ítem para banderas.

Sheet Inventario
A1: Item | B1: FECHA INGRESO INVENTARIO | C1: Nombre | D1: Peso (ct) | E1: Color | F1: Calidad | G1: Cant. | H1: Talla | I1: Medidas | J1: Medidas (valores) | K1: Categoría | L1: costoBaseCOP | M1: precioEmbajadorCOP | N1: precioConscienteCOP | O1: UBICACIÓN | P1: ASESOR | Q1: ESTADO | R1: QR | S1: Colección | T1: CAJA | U1: preponderancia | V1: ASESOR ACTUAL | W1: ESTADO ASESOR | X1: loteId | Y1: mostrarEnCatalogo | Z1: procedencia | AA1: observacion | AB1: rendimientoEsperado | AC1: cantidadEstimada | AD1: nivelRareza | AE1: calificacion | AF1: tipoEsmeralda | AG1: subtipoForm | AH1: tipoJoya | AI1: tecnicaJoya | AJ1: minerales | AK1: complementos | AL1: fotoUrl | AM1: certificadoUrl | AN1: formulaGema | AO1: formulaJoya | AP1: rangoDescuento | AQ1: Peso (gr) | AR1: Costo lote (fórmula) | AS1: Precio x2.6 (fórmula) | AT1: Precio objetivo (modelo) | AU1: Caja: precio venta | AV1: Caja: valor pagado | AW1: Caja: saldo | AX1: Caja: comprador | AY1: Caja: estado contable | AZ1: subLote (grupo) | BA1: Producto (URL) | BB1: Carpeta fotos (Drive) | BC1: Anima: notas relacionadas | BD1: Fuentes | BE1: Notas / conflictos
A2: 1 | B2: 31-oct-2025 | C2: Rey Midas | D2: 1.47 | E2: Verde Natural | F2: COMERCIAL FINA | G2: 1 | H2: Esmeralda | K2: Gema | L2: 244231 | O2: ASESOR | P2: M.Campuzano | Q2: VENDIDA | R2: https://tierramadre.app/p/1 | S2: #4000 | T2: Legalizada | AR2: =IFERROR(VLOOKUP($X2,Lotes!$A:$E,5,FALSE())*$U2,"") | AS2: =IF($L2="","",$L2*2.6) -> 635000.6 | AU2: 635000 | AV2: 635000 | AW2: 0 | AX2: M.Campuzano | AY2: VENDIDO | BA2: https://tierramadre.app/product/1 | BB2: https://drive.google.com/drive/folders/194ctZBJ3jKBQrP1k6LbqwYAwxxY9Y-Zo | BC2: 2026-07-18-rey-midas-item-1 | BD2: Legacy + Fotosintesis/Convex + CajaInventario | BE2: costo estimado = precio/2.6 (costo original igualaba al precio)
A3: 2 | B3: 31-oct-2025 | C3: Las Niñas | D3: 0.43 | E3: Verde Natural | F3: COMERCIAL FINA | G3: 2 | H3: Redonda | K3: Gema | L3: 71154 | O3: ASESOR | P3: M.Echeverry | Q3: VENDIDA | R3: https://tierramadre.app/p/2 | S3: #4000 | T3: Legalizada | AR3: =IFERROR(VLOOKUP($X3,Lotes!$A:$E,5,FALSE())*$U3,"") | AS3: =IF($L3="","",$L3*2.6) -> 185000.4 | AU3: 185000 | AV3: 185000 | AW3: 0 | AX3: M.Echeverry | AY3: VENDIDO | BA3: https://tierramadre.app/product/2 | BB3: https://drive.google.com/drive/folders/1f0pQmqKCoH27iYLaGLojrxNoIMKSGH5a | BC3: 2026-07-18-las-ninas-item-2 | BD3: Legacy + Fotosintesis/Convex + CajaInventario | BE3: costo estimado = precio/2.6 (costo original igualaba al precio)
A4: 3 | B4: 31-oct-2025 | C4: Las Margaritas | D4: 1.36 | E4: Verde Natural | F4: COMERCIAL FINA | G4: 2 | H4: Esmeralda | K4: Gema | L4: 113077 | O4: EMBAJADOR | P4: Isa la Negra Vikinga Warrior Portocarrero | Q4: VENDIDA | R4: https://tierramadre.app/p/3 | S4: #4000 | T4: Pte Fecha x Legalizar | AR4: =IFERROR(VLOOKUP($X4,Lotes!$A:$E,5,FALSE())*$U4,"") | AS4: =IF($L4="","",$L4*2.6) -> 294000.2 | AU4: 294000 | AV4: 294000 | AW4: 294000 | AX4: Isa la Negra Vikinga Warrior Portocarrero | AY4: CARTERA | BA4: https://tierramadre.app/product/3 | BB4: https://drive.google.com/drive/folders/1kXononMMYnH_6D8ogQMy0uy7CpaDSwKF | BC4: 2026-07-18-las-margaritas-item-3 | BD4: Legacy + Fotosintesis/Convex + CajaInventario | BE4: costo estimado = precio/2.6 (costo original igualaba al precio)
A5: 4 | B5: 31-oct-2025 | C5: Los Robles | D5: 1.56 | E5: Verde Natural | F5: COMERCIAL FINA | G5: 2 | H5: Esmeralda | K5: Gema | L5: 259231 | O5: ASESOR | P5: A.Molano | Q5: VENDIDA | R5: https://tierramadre.app/p/4 | S5: #4000 | T5: Legalizada | AR5: =IFERROR(VLOOKUP($X5,Lotes!$A:$E,5,FALSE())*$U5,"") | AS5: =IF($L5="","",$L5*2.6) -> 674000.6 | AU5: 674000 | AV5: 606600 | AW5: 0 | AX5: A.Molano | AY5: VENDIDO | BA5: https://tierramadre.app/product/4 | BB5: https://drive.google.com/drive/folders/1ct_fayajbdnGYyepO4WvlxzzD2mYuePw | BC5: 2026-07-18-los-robles-item-4 | BD5: Legacy + Fotosintesis/Convex + CajaInventario | BE5: costo estimado = precio/2.6 (costo original igualaba al precio)
A6: 5 | B6: 31-oct-2025 | C6: Los Tulipanes | D6: 1.26 | E6: Verde Natural | F6: COMERCIAL SUPERIOR | G6: 2 | H6: Cuadrada | K6: Gema | L6: 191923 | O6: ASESOR | P6: M.Gómez | Q6: VENDIDA | R6: https://tierramadre.app/p/5 | S6: #4000 | T6: Legalizada | AR6: =IFERROR(VLOOKUP($X6,Lotes!$A:$E,5,FALSE())*$U6,"") | AS6: =IF($L6="","",$L6*2.6) -> 498999.8 | AU6: 499000 | AV6: 499000 | AW6: 0 | AX6: M.Gomez | AY6: VENDIDO | BA6: https://tierramadre.app/product/5 | BB6: https://drive.google.com/drive/folders/1Ml10tLHgct3VB2RqrRLx-wKYVONJty1R | BC6: 2026-07-18-los-tulipanes-item-5 | BD6: Legacy + Fotosintesis/Convex + CajaInventario | BE6: Caja (snapshot) registra comprador 'M.Gomez' vs asesor actual 'M.Gómez' — revisar si son ventas distintas o la copia está desactualizada. · costo estimado = precio/2.6 (costo original igualaba al precio)
A7: 6 | B7: 31-oct-2025 | C7: Jardín Escondido | D7: 1.23 | E7: Verde Natural | F7: COMERCIAL SUPERIOR | G7: 1 | H7: Cuadrada | K7: Gema | L7: 170385 | O7: ASESOR | P7: M.Echeverry | Q7: VENDIDA | R7: https://tierramadre.app/p/6 | S7: #4000 | T7: Legalizada | AR7: =IFERROR(VLOOKUP($X7,Lotes!$A:$E,5,FALSE())*$U7,"") | AS7: =IF($L7="","",$L7*2.6) -> 443001 | AU7: 443000 | AV7: 443000 | AW7: 0 | AX7: M.Echeverry | AY7: VENDIDO | BA7: https://tierramadre.app/product/6 | BB7: https://drive.google.com/drive/folders/128cd636PXCN_OJNu7Ml-HWO60E0y3nh1 | BC7: 2026-07-18-jardin-escondido-item-6 | BD7: Legacy + Fotosintesis/Convex + CajaInventario | BE7: costo estimado = precio/2.6 (costo original igualaba al precio)
A8: 7 | B8: 31-oct-2025 | C8: Trilogía | D8: 1.43 | E8: Verde Natural | F8: COMERCIAL SUPERIOR | G8: 3 | H8: Cuadrada | K8: Gema | L8: 218077 | O8: ASESOR | P8: M.Gómez | Q8: VENDIDA | R8: https://tierramadre.app/p/7 | S8: #4000 | T8: Legalizada | AR8: =IFERROR(VLOOKUP($X8,Lotes!$A:$E,5,FALSE())*$U8,"") | AS8: =IF($L8="","",$L8*2.6) -> 567000.2 | AU8: 567000 | AV8: 567000 | AW8: 0 | AX8: M.Gomez | AY8: VENDIDO | BA8: https://tierramadre.app/product/7 | BB8: https://drive.google.com/drive/folders/1C6LBBdS68h22LsCBhGH9likIuIt0ioOJ | BC8: 2026-07-18-trilogia-item-7 | BD8: Legacy + Fotosintesis/Convex + CajaInventario | BE8: Caja (snapshot) registra comprador 'M.Gomez' vs asesor actual 'M.Gómez' — revisar si son ventas distintas o la copia está desactualizada. · costo estimado = precio/2.6 (costo original igualaba al precio)
A9: 8 | B9: 31-oct-2025 | C9: Bambú | D9: 0.83 | E9: Verde Natural | F9: COMERCIAL SUPERIOR | G9: 1 | H9: Cuadrada | K9: Gema | L9: 115000 | O9: ASESOR | P9: M.Campuzano | Q9: VENDIDA | R9: https://tierramadre.app/p/8 | S9: #4000 | T9: Legalizada | AR9: =IFERROR(VLOOKUP($X9,Lotes!$A:$E,5,FALSE())*$U9,"") | AS9: =IF($L9="","",$L9*2.6) -> 299000 | AU9: 299000 | AV9: 299000 | AW9: 0 | AX9: M.Campuzano | AY9: VENDIDO | BA9: https://tierramadre.app/product/8 | BB9: https://drive.google.com/drive/folders/1_MmIVPvsjdJvwFiJHj9b8hux-UU4HrB8 | BC9: 2026-07-18-bambu-item-8 | BD9: Legacy + Fotosintesis/Convex + CajaInventario | BE9: costo estimado = precio/2.6 (costo original igualaba al precio)
A10: 9 | B10: 31-oct-2025 | C10: Turquesa | D10: 0.66 | E10: Verde Natural | F10: COMERCIAL ESTÁNDAR | G10: 1 | H10: Esmeralda | K10: Gema | L10: 91538 | O10: EMBAJADOR | P10: Isa la Negra Vikinga Warrior Portocarrero | Q10: VENDIDA | R10: https://tierramadre.app/p/9 | S10: #4000 | T10: Legalizada | AR10: =IFERROR(VLOOKUP($X10,Lotes!$A:$E,5,FALSE())*$U10,"") | AS10: =IF($L10="","",$L10*2.6) -> 237998.8 | AU10: 238000 | AV10: 238000 | AW10: 0 | AX10: Isa la Negra Vikinga Warrior Portocarrero | AY10: VENDIDO | BA10: https://tierramadre.app/product/9 | BB10: https://drive.google.com/drive/folders/1i7hpPgZYv3ypngGeSLG2vZZOOcMOKocb | BC10: 2026-07-18-turquesa-item-9 | BD10: Legacy + Fotosintesis/Convex + CajaInventario | BE10: costo estimado = precio/2.6 (costo original igualaba al precio)
A11: 10 | B11: 31-oct-2025 | C11: Jazmin | D11: 0.99 | E11: Verde Natural | F11: COMERCIAL ESTÁNDAR | G11: 1 | H11: Esmeralda | K11: Gema | L11: 89500 | O11: OFI.CALI | P11: M.Campuzano | Q11: DISPONIBLE | R11: https://tierramadre.app/p/10 | S11: #4000 | X11: C-058 | AF11: Gola | AR11: =IFERROR(VLOOKUP($X11,Lotes!$A:$E,5,FALSE())*$U11,"") -> 0 | AS11: =IF($L11="","",$L11*2.6) -> 232700 | AU11: 358000 | AV11: 358000 | AW11: 358000 | AX11: Tierra Madre | AY11: Disponible | BA11: https://tierramadre.app/product/10 | BB11: https://drive.google.com/drive/folders/1UDgx_-NJ4dzukfdAEZ6Docmqb9mafGxS | BC11: 2026-07-13-jazmin-item-10 · 2026-07-17-jazmin-item-10-vendida | BD11: Legacy + Fotosintesis/Convex + ModeloPrecios + CajaInventario | BE11: Calidad difiere: legacy=Comercial Estándar vs modeloPrecios=C. Estándar | Caja (snapshot) registra comprador 'Tierra Madre' vs asesor actual 'M.Campuzano' — revisar si son ventas distintas o la copia está desactualizada.
A12: 11 | B12: 31-oct-2025 | C12: Rosario | D12: 0.81 | E12: Verde Natural | F12: COMERCIAL ESTÁNDAR | G12: 1 | H12: Redonda | K12: Gema | L12: 113077 | O12: ASESOR | P12: A.Molano | Q12: VENDIDA | R12: https://tierramadre.app/p/11 | S12: #4000 | T12: Legalizada | AR12: =IFERROR(VLOOKUP($X12,Lotes!$A:$E,5,FALSE())*$U12,"") | AS12: =IF($L12="","",$L12*2.6) -> 294000.2 | AU12: 294000 | AV12: 264600 | AW12: 0 | AX12: A.Molano | AY12: VENDIDO | BA12: https://tierramadre.app/product/11 | BB12: https://drive.google.com/drive/folders/1Ae8JfDOC4WH7JWR9YzCnCEceMnuYPlDZ | BC12: 2026-07-18-rosario-item-11 | BD12: Legacy + Fotosintesis/Convex + CajaInventario | BE12: costo estimado = precio/2.6 (costo original igualaba al precio)
A13: 12 | B13: 31-oct-2025 | C13: Baby Green | D13: 0.46 | E13: Verde Limón | F13: COMERCIAL SUPERIOR | G13: 1 | H13: Redonda | K13: Gema | L13: 65385 | O13: ASESOR | P13: A.Molano | Q13: VENDIDA | R13: https://tierramadre.app/p/12 | S13: #4000 | T13: Legalizada | AR13: =IFERROR(VLOOKUP($X13,Lotes!$A:$E,5,FALSE())*$U13,"") | AS13: =IF($L13="","",$L13*2.6) -> 170001 | AU13: 170000 | AV13: 125800 | AW13: 0 | AX13: A.Molano | AY13: VENDIDO | BA13: https://tierramadre.app/product/12 | BB13: https://drive.google.com/drive/folders/11lpxWncpyBq_YoAs22kOIOrz_greUMmn | BC13: 2026-07-18-baby-green-item-12 | BD13: Legacy + Fotosintesis/Convex + CajaInventario | BE13: costo estimado = precio/2.6 (costo original igualaba al precio)
A14: 13 | B14: 31-oct-2025 | C14: Amazonas | D14: 0.41 | E14: Verde Limón | F14: COMERCIAL FINA | G14: 1 | H14: Ovalo | K14: Gema | L14: 63846 | O14: EMBAJADOR | P14: Isa la Negra Vikinga Warrior Portocarrero | Q14: VENDIDA | R14: https://tierramadre.app/p/13 | S14: #4000 | T14: Legalizada | AR14: =IFERROR(VLOOKUP($X14,Lotes!$A:$E,5,FALSE())*$U14,"") | AS14: =IF($L14="","",$L14*2.6) -> 165999.6 | AU14: 166000 | AV14: 166000 | AW14: 0 | AX14: Isa la Negra Vikinga Warrior Portocarrero | AY14: VENDIDO | BA14: https://tierramadre.app/product/13 | BB14: https://drive.google.com/drive/folders/129kesHdlmj7_0yUitRhzsYGinKqx_RdZ | BC14: 2026-07-18-amazonas-item-13 | BD14: Legacy + Fotosintesis/Convex + CajaInventario | BE14: costo estimado = precio/2.6 (costo original igualaba al precio)
A15: 14 | B15: 31-oct-2025 | C15: Leticia | D15: 0.33 | E15: Verde Limón | F15: COMERCIAL FINA | G15: 1 | H15: Redonda | K15: Gema | L15: 51538 | O15: ASESOR | P15: M.Campuzano | Q15: VENDIDA | R15: https://tierramadre.app/p/14 | S15: #4000 | T15: Legalizada | AR15: =IFERROR(VLOOKUP($X15,Lotes!$A:$E,5,FALSE())*$U15,"") | AS15: =IF($L15="","",$L15*2.6) -> 133998.8 | AU15: 134000 | AV15: 134000 | AW15: 0 | AX15: Tierra Madre | AY15: VENDIDO | BA15: https://tierramadre.app/product/14 | BB15: https://drive.google.com/drive/folders/1ZMZ6uPiT2bgQl9Y1GfKgM7QWJUnfczX_ | BC15: 2026-07-18-leticia-item-14 | BD15: Legacy + Fotosintesis/Convex + CajaInventario | BE15: Caja (snapshot) registra comprador 'Tierra Madre' vs asesor actual 'M.Campuzano' — revisar si son ventas distintas o la copia está desactualizada. · costo estimado = precio/2.6 (costo original igualaba al precio)
A16: 15 | B16: 31-oct-2025 | C16: Madre Selva | D16: 0.75 | E16: Verde Limón | F16: COMERCIAL FINA | G16: 1 | H16: Cuadrada | K16: Gema | L16: 116538 | O16: ASESOR | P16: A.Molano | Q16: VENDIDA | R16: https://tierramadre.app/p/15 | S16: #4000 | T16: Legalizada | AR16: =IFERROR(VLOOKUP($X16,Lotes!$A:$E,5,FALSE())*$U16,"") | AS16: =IF($L16="","",$L16*2.6) -> 302998.8 | AU16: 303000 | AV16: 224220 | AW16: 0 | AX16: A.Molano | AY16: VENDIDO | BA16: https://tierramadre.app/product/15 | BB16: https://drive.google.com/drive/folders/1O-7j5NRL1CdfqmIr7fAG6HGO3VJPK3mt | BC16: 2026-07-18-madre-selva-item-15 | BD16: Legacy + Fotosintesis/Convex + CajaInventario | BE16: costo estimado = precio/2.6 (costo original igualaba al precio)
A17: 16 | B17: 31-oct-2025 | C17: Pacífico | D17: 0.55 | E17: Verde Limón | F17: COMERCIAL FINA | G17: 1 | H17: Cuadrada | K17: Gema | L17: 85385 | O17: ASESOR | P17: A.Molano | Q17: VENDIDA | R17: https://tierramadre.app/p/16 | S17: #4000 | T17: Legalizada | AR17: =IFERROR(VLOOKUP($X17,Lotes!$A:$E,5,FALSE())*$U17,"") | AS17: =IF($L17="","",$L17*2.6) -> 222001 | AU17: 222000 | AV17: 164280 | AW17: 0 | AX17: A.Molano | AY17: VENDIDO | BA17: https://tierramadre.app/product/16 | BB17: https://drive.google.com/drive/folders/1nFmRjpaKiJegs_yj-ZhoOsY8VvUK4Mr0 | BC17: 2026-07-18-pacifico-item-16 | BD17: Legacy + Fotosintesis/Convex + CajaInventario | BE17: costo estimado = precio/2.6 (costo original igualaba al precio)
A18: 17 | B18: 31-oct-2025 | C18: Mística | D18: 0.38 | E18: Verde Limón | F18: COMERCIAL SUPERIOR | G18: 1 | H18: Lágrima | K18: Gema | L18: 154000 | O18: ASESOR | P18: M.Gómez | Q18: VENDIDA | R18: https://tierramadre.app/p/17 | S18: #4000 | T18: Legalizada | AR18: =IFERROR(VLOOKUP($X18,Lotes!$A:$E,5,FALSE())*$U18,"") | AS18: =IF($L18="","",$L18*2.6) -> 400400 | AU18: 231000 | AV18: 147840 | AW18: 0 | AX18: M.Gomez | AY18: VENDIDO | BA18: https://tierramadre.app/product/17 | BB18: https://drive.google.com/drive/folders/1AGZwNq6hnFV6zFgJVZWSkVDOC4c5Kq4J | BC18: 2026-07-18-mistica-item-17 | BD18: Legacy + Fotosintesis/Convex + CajaInventario | BE18: Caja (snapshot) registra comprador 'M.Gomez' vs asesor actual 'M.Gómez' — revisar si son ventas distintas o la copia está desactualizada.
A19: 18 | B19: 31-oct-2025 | C19: Pachitas | D19: 0.74 | E19: Verde Limón | F19: COMERCIAL FINA | G19: 2 | H19: Cuadrada | K19: Gema | L19: 299000 | O19: ASESOR | P19: M.Gómez | Q19: VENDIDA | R19: https://tierramadre.app/p/18 | S19: #4000 | T19: Pte Legalizar | AR19: =IFERROR(VLOOKUP($X19,Lotes!$A:$E,5,FALSE())*$U19,"") | AS19: =IF($L19="","",$L19*2.6) -> 777400 | AU19: 448500 | AV19: 448500 | AW19: 296500 | AX19: M.Gomez | AY19: CARTERA | BA19: https://tierramadre.app/product/18 | BB19: https://drive.google.com/drive/folders/1V9EK9N6WjIzsImGztuqojvoYtpohLTrS | BC19: 2026-07-18-pachitas-item-18 | BD19: Legacy + Fotosintesis/Convex + CajaInventario | BE19: Caja (snapshot) registra comprador 'M.Gomez' vs asesor actual 'M.Gómez' — revisar si son ventas distintas o la copia está desactualizada.
A20: 19 | B20: 31-oct-2025 | C20: 5 Estrellas | D20: 2.14 | E20: Verde Limón | F20: COMERCIAL FINA | G20: 5 | H20: Cuadrada | K20: Gema | L20: 304231 | O20: ASESOR | P20: M.Gómez | Q20: VENDIDA | R20: https://tierramadre.app/p/19 | S20: #4000 | T20: Legalizada | AR20: =IFERROR(VLOOKUP($X20,Lotes!$A:$E,5,FALSE())*$U20,"") | AS20: =IF($L20="","",$L20*2.6) -> 791000.6 | AU20: 791000 | AV20: 780796.1 | AW20: 796.1 | AX20: M.Gomez | AY20: VENDIDO | BA20: https://tierramadre.app/product/19 | BB20: https://drive.google.com/drive/folders/1hWzLBarjP25vCmvxEnDtbm22Cln7Sgq8 | BC20: 2026-07-18-5-estrellas-item-19 | BD20: Legacy + Fotosintesis/Convex + CajaInventario | BE20: Caja (snapshot) registra comprador 'M.Gomez' vs asesor actual 'M.Gómez' — revisar si son ventas distintas o la copia está desactualizada. · costo estimado = precio/2.6 (costo original igualaba al precio)
A21: 20 | B21: 31-oct-2025 | C21: 2 Pinticas | D21: 0.73 | E21: Verde Limón | F21: COMERCIAL FINA | G21: 2 | H21: Esmeralda | K21: Gema | L21: 270000 | O21: ASESOR | P21: Paola Daza | Q21: VENDIDA | R21: https://tierramadre.app/p/20 | S21: #4000 | T21: Legalizada | AR21: =IFERROR(VLOOKUP($X21,Lotes!$A:$E,5,FALSE())*$U21,"") | AS21: =IF($L21="","",$L21*2.6) -> 702000 | AU21: 405000 | AV21: 392850 | AW21: 0 | AX21: Paola Daza | AY21: VENDIDO | BA21: https://tierramadre.app/product/20 | BB21: https://drive.google.com/drive/folders/1uEbSr_4XGRexukQBE3gtST6NCViBi_r8 | BC21: 2026-07-18-2-pinticas-item-20 | BD21: Legacy + Fotosintesis/Convex + CajaInventario
A22: 21 | B22: 31-oct-2025 | C22: Dualidad | D22: 1.63 | E22: Verde Limón | F22: COMERCIAL ESTÁNDAR | G22: 2 | H22: Cuadrada | K22: Gema | L22: 210769 | O22: ASESOR | P22: A.Molano | Q22: VENDIDA | R22: https://tierramadre.app/p/21 | S22: #4000 | T22: Legalizada | AR22: =IFERROR(VLOOKUP($X22,Lotes!$A:$E,5,FALSE())*$U22,"") | AS22: =IF($L22="","",$L22*2.6) -> 547999.4 | AU22: 548000 | AV22: 411000 | AW22: 0 | AX22: A.Molano | AY22: VENDIDO | BA22: https://tierramadre.app/product/21 | BB22: https://drive.google.com/drive/folders/1fpGsWEih1WDqEYbVpKLXnScNMxdu_BoP | BC22: 2026-07-18-dualidad-item-21 | BD22: Legacy + Fotosintesis/Convex + CajaInventario | BE22: costo estimado = precio/2.6 (costo original igualaba al precio)
A23: 22 | B23: 31-oct-2025 | C23: Brasil | D23: 1.14 | E23: Verde Limón | F23: COMERCIAL ESTÁNDAR | G23: 1 | H23: Redonda | K23: Gema | L23: 147308 | O23: ASESOR | P23: A.Molano | Q23: VENDIDA | R23: https://tierramadre.app/p/22 | S23: #4000 | T23: Legalizada | AR23: =IFERROR(VLOOKUP($X23,Lotes!$A:$E,5,FALSE())*$U23,"") | AS23: =IF($L23="","",$L23*2.6) -> 383000.8 | AU23: 383000 | AV23: 283420 | AW23: 0 | AX23: A.Molano | AY23: VENDIDO | BA23: https://tierramadre.app/product/22 | BB23: https://drive.google.com/drive/folders/1UsrsRKJQIUF-T2t4LyeFMhMXut5WUgMv | BC23: 2026-07-18-brasil-item-22 | BD23: Legacy + Fotosintesis/Convex + CajaInventario | BE23: costo estimado = precio/2.6 (costo original igualaba al precio)
A24: 23 | B24: 31-oct-2025 | C24: Guajira | D24: 0.58 | E24: Verde Limón | F24: COMERCIAL ESTÁNDAR | G24: 1 | H24: Redonda | K24: Gema | L24: 195000 | O24: ASESOR | P24: Pablito | Q24: VENDIDA | R24: https://tierramadre.app/p/23 | S24: #4000 | T24: Legalizada | AR24: =IFERROR(VLOOKUP($X24,Lotes!$A:$E,5,FALSE())*$U24,"") | AS24: =IF($L24="","",$L24*2.6) -> 507000 | AU24: 234000 | AV24: 200070 | AW24: 70 | AX24: Pablito | AY24: VENDIDO | BA24: https://tierramadre.app/product/23 | BB24: https://drive.google.com/drive/folders/1NqWuRiC1oc5C-vziwQR5flgv5n2pbAwb | BC24: 2026-07-18-guajira-item-23 | BD24: Legacy + Fotosintesis/Convex + CajaInventario
A25: 24 | B25: 31-oct-2025 | C25: Aqua | D25: 0.44 | E25: Verde Limón | F25: COMERCIAL ESTÁNDAR | G25: 1 | H25: Lágrima | K25: Gema | L25: 56923 | O25: ASESOR | P25: M.Campuzano | Q25: VENDIDA | R25: https://tierramadre.app/p/24 | S25: #4000 | T25: Legalizada | AR25: =IFERROR(VLOOKUP($X25,Lotes!$A:$E,5,FALSE())*$U25,"") | AS25: =IF($L25="","",$L25*2.6) -> 147999.8 | AU25: 148000 | AV25: 148000 | AW25: 0 | AX25: Tierra Madre | AY25: VENDIDO | BA25: https://tierramadre.app/product/24 | BB25: https://drive.google.com/drive/folders/1M688e1omkth5-S86LbXHSgIUd0jCvXD_ | BC25: 2026-07-18-aqua-item-24 | BD25: Legacy + Fotosintesis/Convex + CajaInventario | BE25: Caja (snapshot) registra comprador 'Tierra Madre' vs asesor actual 'M.Campuzano' — revisar si son ventas distintas o la copia está desactualizada. · costo estimado = precio/2.6 (costo original igualaba al precio)
A26: 25 | B26: 31-oct-2025 | C26: Las Emperatrices | D26: 0.41 | E26: Verde Menta | F26: COMERCIAL FINA | G26: 2 | H26: Cuadrada | K26: Gema | L26: 63846 | O26: ASESOR | P26: A.Molano | Q26: VENDIDA | R26: https://tierramadre.app/p/25 | S26: #4000 | T26: Legalizada | AR26: =IFERROR(VLOOKUP($X26,Lotes!$A:$E,5,FALSE())*$U26,"") | AS26: =IF($L26="","",$L26*2.6) -> 165999.6 | AU26: 166000 | AV26: 122840 | AW26: 0 | AX26: A.Molano | AY26: VENDIDO | BA26: https://tierramadre.app/product/25 | BB26: https://drive.google.com/drive/folders/11JzkwLX7sllytq36gOy557XUrIcuEOpS | BC26: 2026-07-18-las-emperatrices-item-25 | BD26: Legacy + Fotosintesis/Convex + CajaInventario | BE26: costo estimado = precio/2.6 (costo original igualaba al precio)
A27: 26 | B27: 31-oct-2025 | C27: Madre e Hija | D27: 0.21 | E27: Verde Menta | F27: COMERCIAL FINA | G27: 2 | H27: Esmeralda | K27: Gema | L27: 32692 | O27: EMBAJADOR | P27: Isa la Negra Vikinga Warrior Portocarrero | Q27: VENDIDA | R27: https://tierramadre.app/p/26 | S27: #4000 | T27: Legalizada | AR27: =IFERROR(VLOOKUP($X27,Lotes!$A:$E,5,FALSE())*$U27,"") | AS27: =IF($L27="","",$L27*2.6) -> 84999.2 | AU27: 85000 | AV27: 85000 | AW27: 0 | AX27: Isa la Negra Vikinga Warrior Portocarrero | AY27: VENDIDO | BA27: https://tierramadre.app/product/26 | BB27: https://drive.google.com/drive/folders/1LXXT8Kc55Rle2B4YP7DMm9Bd0W77-I5c | BC27: 2026-07-18-madre-e-hija-item-26 | BD27: Legacy + Fotosintesis/Convex + CajaInventario | BE27: costo estimado = precio/2.6 (costo original igualaba al precio)
A28: 27 | B28: 31-oct-2025 | C28: Hijos de la Tierra | D28: 0.13 | E28: Verde Menta | F28: COMERCIAL FINA | G28: 8 | H28: Redonda | K28: Gema | L28: 160769 | O28: ASESOR | P28: M.Gómez | Q28: VENDIDA | R28: https://tierramadre.app/p/27 | S28: #4000 | T28: Legalizada | AR28: =IFERROR(VLOOKUP($X28,Lotes!$A:$E,5,FALSE())*$U28,"") | AS28: =IF($L28="","",$L28*2.6) -> 417999.4 | AU28: 418000 | AV28: 249128 | AW28: 0 | AX28: M.Gomez | AY28: VENDIDO | BA28: https://tierramadre.app/product/27 | BB28: https://drive.google.com/drive/folders/1Notlg6O4K2JcJ1OJtwicXEmGyk9nGmub | BC28: 2026-07-18-hijos-de-la-tierra-item-27 | BD28: Legacy + Fotosintesis/Convex + CajaInventario | BE28: Caja (snapshot) registra comprador 'M.Gomez' vs asesor actual 'M.Gómez' — revisar si son ventas distintas o la copia está desactualizada. · costo estimado = precio/2.6 (costo original igualaba al precio)
A29: 28 | B29: 31-oct-2025 | C29: Las 3 Marías | D29: 0.33 | E29: Verde Menta | F29: COMERCIAL FINA | G29: 3 | H29: Redonda | K29: Gema | L29: 51538 | O29: ASESOR | P29: Jennifer.Florez | Q29: VENDIDA | R29: https://tierramadre.app/p/28 | S29: #4000 | T29: Legalizada | AR29: =IFERROR(VLOOKUP($X29,Lotes!$A:$E,5,FALSE())*$U29,"") | AS29: =IF($L29="","",$L29*2.6) -> 133998.8 | AU29: 134000 | AV29: 85760 | AW29: 0 | AX29: Jenifer.Florez | AY29: VENDIDO | BA29: https://tierramadre.app/product/28 | BB29: https://drive.google.com/drive/folders/1T5Co05DVsSoOcuCglRd9RUB_EIVGwnSl | BC29: 2026-07-18-las-3-marias-item-28 | BD29: Legacy + Fotosintesis/Convex + CajaInventario | BE29: Caja (snapshot) registra comprador 'Jenifer.Florez' vs asesor actual 'Jennifer.Florez' — revisar si son ventas distintas o la copia está desactualizada. · costo estimado = precio/2.6 (costo original igualaba al precio)
A30: 29 | B30: 11-nov-2025 | C30: Hijos del sol | D30: 1.73 | E30: Verde Limón | F30: COMERCIAL SÚPER FINA | G30: 2 | H30: Esmeralda | I30: Largo x Ancho | J30: 6.2 × 5.4 mm | K30: Gema | L30: 293077 | O30: ASESOR | P30: M.Campuzano | Q30: VENDIDA | R30: https://tierramadre.app/p/29 | S30: 11:11 | T30: Pte Fecha x Legalizar | AR30: =IFERROR(VLOOKUP($X30,Lotes!$A:$E,5,FALSE())*$U30,"") | AS30: =IF($L30="","",$L30*2.6) -> 762000.2 | AU30: 762000 | AV30: 762000 | AW30: 762000 | AX30: M.Campuzano | AY30: CARTERA | BA30: https://tierramadre.app/product/29 | BB30: https://drive.google.com/drive/folders/1nU2FfG06DAMolYiu8U5EMZ6UEA-I9gOl | BC30: 2026-07-15-hijos-del-sol-item-29 | BD30: Legacy + Fotosintesis/Convex + CajaInventario | BE30: costo estimado = precio/2.6 (costo original igualaba al precio)
A31: 30 | B31: 11-nov-2025 | C31: Amor Eterno | D31: 1.08 | E31: Verde Limón | F31: COMERCIAL SÚPER FINA | G31: 2 | H31: Esmeralda | I31: Largo x Ancho | J31: 6.2 × 4.3 mm | K31: Gema | L31: 240385 | O31: ASESOR | P31: Jennifer.Florez | Q31: VENDIDA | R31: https://tierramadre.app/p/30 | S31: 11:11 | T31: Legalizada | AR31: =IFERROR(VLOOKUP($X31,Lotes!$A:$E,5,FALSE())*$U31,"") | AS31: =IF($L31="","",$L31*2.6) -> 625001 | AU31: 625000 | AV31: 400000 | AW31: 0 | AX31: Jenifer.Florez | AY31: VENDIDO | BA31: https://tierramadre.app/product/30 | BB31: https://drive.google.com/drive/folders/1szKVIxqzH4rULLps4t7uEK87fvZrQPAz | BC31: 2026-07-18-amor-eterno-item-30 | BD31: Legacy + Fotosintesis/Convex + CajaInventario | BE31: peso ct recuperado de serial Excel · Caja (snapshot) registra comprador 'Jenifer.Florez' vs asesor actual 'Jennifer.Florez' — revisar si son ventas distintas o la copia está desactualizada. · costo estimado = precio/2.6 (costo original igualaba al precio)
A32: 31 | B32: 11-nov-2025 | C32: Alma Verde | D32: 0.48 | E32: Verde Limón | F32: COMERCIAL SÚPER FINA | G32: 1 | H32: Cuadrada | I32: Largo x Ancho | J32: 5.1 × 4.4 mm | K32: Gema | L32: 85385 | O32: ASESOR | P32: A.Molano | Q32: VENDIDA | R32: https://tierramadre.app/p/31 | S32: 11:11 | T32: Legalizada | AR32: =IFERROR(VLOOKUP($X32,Lotes!$A:$E,5,FALSE())*$U32,"") | AS32: =IF($L32="","",$L32*2.6) -> 222001 | AU32: 222000 | AV32: 164280 | AW32: 0 | AX32: A.Molano | AY32: VENDIDO | BA32: https://tierramadre.app/product/31 | BB32: https://drive.google.com/drive/folders/1iXzJMscyh24O_lq5xgd1n549HpKfwzwJ | BC32: 2026-07-18-alma-verde-item-31 | BD32: Legacy + Fotosintesis/Convex + CajaInventario | BE32: costo estimado = precio/2.6 (costo original igualaba al precio)
A33: 32 | B33: 11-nov-2025 | C33: Venus | D33: 0.43 | E33: Verde Limón | F33: COMERCIAL SÚPER FINA | G33: 1 | H33: Esmeralda | I33: Largo x Ancho | J33: 4 × 5 mm | K33: Gema | L33: 76538 | O33: ASESOR | P33: A.Molano | Q33: VENDIDA | R33: https://tierramadre.app/p/32 | S33: 11:11 | T33: Legalizada | AR33: =IFERROR(VLOOKUP($X33,Lotes!$A:$E,5,FALSE())*$U33,"") | AS33: =IF($L33="","",$L33*2.6) -> 198998.8 | AU33: 199000 | AV33: 35820 | AW33: -223 | AX33: A.Molano | AY33: VENDIDO | BA33: https://tierramadre.app/product/32 | BB33: https://drive.google.com/drive/folders/1K516L8m71wHAMHjSgsk-uhVPFaMYJ-bK | BC33: 2026-07-18-venus-item-32 | BD33: Legacy + Fotosintesis/Convex + CajaInventario | BE33: costo estimado = precio/2.6 (costo original igualaba al precio)
A34: 33 | B34: 11-nov-2025 | C34: Diosa de la Laguna | D34: 0.45 | E34: Verde Limón | F34: COMERCIAL SÚPER FINA | G34: 1 | H34: Ovalo | I34: Largo x Ancho | J34: 4 × 5 mm | K34: Gema | L34: 111923 | O34: ASESOR | P34: A.Molano | Q34: VENDIDA | R34: https://tierramadre.app/p/33 | S34: 11:11 | T34: Legalizada | AR34: =IFERROR(VLOOKUP($X34,Lotes!$A:$E,5,FALSE())*$U34,"") | AS34: =IF($L34="","",$L34*2.6) -> 290999.8 | AU34: 291000 | AV34: 215340 | AW34: 0 | AX34: A.Molano | AY34: VENDIDO | BA34: https://tierramadre.app/product/33 | BB34: https://drive.google.com/drive/folders/12tstqF-Q4zLQJPs97OM224JhiM19pOi3 | BC34: 2026-07-18-diosa-de-la-laguna-item-33 | BD34: Legacy + Fotosintesis/Convex + CajaInventario | BE34: costo estimado = precio/2.6 (costo original igualaba al precio)
A35: 34 | B35: 11-nov-2025 | C35: Gaia | D35: 0.55 | E35: Verde Limón | F35: COMERCIAL SÚPER FINA | G35: 1 | H35: Redonda | I35: Diámetro | J35: 52 mm | K35: Gema | L35: 105385 | O35: ASESOR | P35: J.I.Florez | Q35: VENDIDA | R35: https://tierramadre.app/p/34 | S35: 11:11 | T35: Legalizada | AR35: =IFERROR(VLOOKUP($X35,Lotes!$A:$E,5,FALSE())*$U35,"") | AS35: =IF($L35="","",$L35*2.6) -> 274001 | AU35: 274000 | AV35: 175360 | AW35: 0 | AX35: J.I.Florez | AY35: VENDIDO | BA35: https://tierramadre.app/product/34 | BB35: https://drive.google.com/drive/folders/1TCCqfotVP1NaI_WQGfgWMV0_2D6bswku | BC35: 2026-07-18-gaia-item-34 | BD35: Legacy + Fotosintesis/Convex + CajaInventario | BE35: costo estimado = precio/2.6 (costo original igualaba al precio)
A36: 35 | B36: 11-nov-2025 | C36: Inspiración Divina | D36: 0.47 | E36: Verde Limón | F36: FINA ESENCIAL | G36: 1 | H36: Ovalo | I36: Largo x Ancho | J36: 4.9 × 4.1 mm | K36: Gema | L36: 117000 | O36: ASESOR | P36: A.Molano | Q36: VENDIDA | R36: https://tierramadre.app/p/35 | S36: 11:11 | T36: Legalizada | AR36: =IFERROR(VLOOKUP($X36,Lotes!$A:$E,5,FALSE())*$U36,"") | AS36: =IF($L36="","",$L36*2.6) -> 304200 | AU36: 304200 | AV36: 225108 | AW36: 0 | AX36: A.Molano | AY36: VENDIDO | BA36: https://tierramadre.app/product/35 | BB36: https://drive.google.com/drive/folders/1swjdgJD9GqwqhzMnhwg8FiClvZHFQ_EY | BC36: 2026-07-18-inspiracion-divina-item-35 | BD36: Legacy + Fotosintesis/Convex + CajaInventario | BE36: costo estimado = precio/2.6 (costo original igualaba al precio)
A37: 36 | B37: 11-nov-2025 | C37: Lunera | D37: 0.46 | E37: Verde Limón | F37: COMERCIAL SUPERIOR | G37: 1 | H37: Ovalo | I37: Largo x Ancho | J37: 5.0 × 4.3 mm | K37: Gema | L37: 78846 | O37: ASESOR | P37: A.Molano | Q37: VENDIDA | R37: https://tierramadre.app/p/36 | S37: 11:11 | T37: Legalizada | AR37: =IFERROR(VLOOKUP($X37,Lotes!$A:$E,5,FALSE())*$U37,"") | AS37: =IF($L37="","",$L37*2.6) -> 204999.6 | AU37: 205000 | AV37: 151700 | AW37: 0 | AX37: A.Molano | AY37: VENDIDO | BA37: https://tierramadre.app/product/36 | BB37: https://drive.google.com/drive/folders/1UAx_59A5wbey4ALZxhcbj28uU_Lg54xL | BC37: 2026-07-18-lunera-item-36 | BD37: Legacy + Fotosintesis/Convex + CajaInventario | BE37: costo estimado = precio/2.6 (costo original igualaba al precio)
A38: 37 | B38: 11-nov-2025 | C38: Ojo de Zeus | D38: 0.35 | E38: Verde Limón | F38: COMERCIAL FINA | G38: 1 | H38: Redonda | I38: Diámetro | J38: 4.8 mm | K38: Gema | L38: 64615 | O38: EMBAJADOR | P38: Isa la Negra Vikinga Warrior Portocarrero | Q38: VENDIDA | R38: https://tierramadre.app/p/37 | S38: 11:11 | T38: Pte Fecha x Legalizar | AR38: =IFERROR(VLOOKUP($X38,Lotes!$A:$E,5,FALSE())*$U38,"") | AS38: =IF($L38="","",$L38*2.6) -> 167999 | AU38: 168000 | AV38: 168000 | AW38: 168000 | AX38: Isa la Negra Vikinga Warrior Portocarrero | AY38: CARTERA | BA38: https://tierramadre.app/product/37 | BB38: https://drive.google.com/drive/folders/1JegA-Khcl-NBd-I-N8YyvhvColhdXvaa | BC38: 2026-07-18-ojo-de-zeus-item-37 | BD38: Legacy + Fotosintesis/Convex + CajaInventario | BE38: costo estimado = precio/2.6 (costo original igualaba al precio)
A39: 38 | B39: 11-nov-2025 | C39: Infinito | D39: 0.5 | E39: Verde Limón | F39: COMERCIAL FINA | G39: 1 | H39: Cuadrada | I39: Largo x Ancho | J39: 4.8 × 4.8 mm | K39: Gema | L39: 240000 | O39: ASESOR | P39: K.Pineda | Q39: VENDIDA | R39: https://tierramadre.app/p/38 | S39: 11:11 | T39: Legalizada | AR39: =IFERROR(VLOOKUP($X39,Lotes!$A:$E,5,FALSE())*$U39,"") | AS39: =IF($L39="","",$L39*2.6) -> 624000 | AU39: 360000 | AV39: 288000 | AW39: 0 | AX39: K.Pineda | AY39: VENDIDO | BA39: https://tierramadre.app/product/38 | BB39: https://drive.google.com/drive/folders/1aGb44P2X_RXl-MO9BbyWsCJ4q9ndQkis | BC39: 2026-07-18-infinito-item-38 | BD39: Legacy + Fotosintesis/Convex + CajaInventario
A40: 39 | B40: 11-nov-2025 | C40: Galaxia | D40: 0.55 | E40: Verde Limón | F40: COMERCIAL SUPERIOR | G40: 1 | H40: Redonda | I40: Largo x Ancho | J40: 55 mm | K40: Gema | L40: 73077 | O40: ASESOR | P40: M.Echeverry | Q40: VENDIDA | R40: https://tierramadre.app/p/39 | S40: 11:11 | AR40: =IFERROR(VLOOKUP($X40,Lotes!$A:$E,5,FALSE())*$U40,"") | AS40: =IF($L40="","",$L40*2.6) -> 190000.2 | AU40: 190000 | AV40: 190000 | AW40: 0 | AX40: M.Echeverry | AY40: VENDIDO | BA40: https://tierramadre.app/product/39 | BB40: https://drive.google.com/drive/folders/1Rd8K4VUjmrTZT0neqkRQKK5umtGSAepa | BC40: 2026-07-18-galaxia-item-39 | BD40: Legacy + Fotosintesis/Convex + CajaInventario | BE40: costo estimado = precio/2.6 (costo original igualaba al precio)
A41: 40 | B41: 11-nov-2025 | C41: Resplandor | D41: 0.48 | E41: Verde Limón | F41: COMERCIAL SUPERIOR | G41: 1 | H41: Esmeralda | I41: Largo x Ancho | J41: 5.6 × 4.2 mm | K41: Gema | L41: 85385 | O41: ASESOR | P41: L.A.Ospina | Q41: VENDIDA | R41: https://tierramadre.app/p/40 | S41: 11:11 | T41: Legalizada | AR41: =IFERROR(VLOOKUP($X41,Lotes!$A:$E,5,FALSE())*$U41,"") | AS41: =IF($L41="","",$L41*2.6) -> 222001 | AU41: 222000 | AV41: 177600 | AW41: 0 | AX41: L.A.Ospina | AY41: VENDIDO | BA41: https://tierramadre.app/product/40 | BB41: https://drive.google.com/drive/folders/1YTif5tlCEvuIAMyZAxVNqjONBv2fDhRZ | BC41: 2026-07-18-resplandor-item-40 | BD41: Legacy + Fotosintesis/Convex + CajaInventario | BE41: costo estimado = precio/2.6 (costo original igualaba al precio)
A42: 41 | B42: 12-nov-2025 | C42: L:A Anillo Corona | E42: Verde Menta | F42: Plata - comercial | G42: 1 | H42: 5 | K42: Anillo en Plata | L42: 146154 | O42: ASESOR | P42: M.Restrepo | Q42: VENDIDA | R42: https://tierramadre.app/p/41 | S42: Fénix | T42: Legalizada | AR42: =IFERROR(VLOOKUP($X42,Lotes!$A:$E,5,FALSE())*$U42,"") | AS42: =IF($L42="","",$L42*2.6) -> 380000.4 | AU42: 380000 | AV42: 380000 | AW42: 0 | AX42: M.Restrepo | AY42: VENDIDO | BA42: https://tierramadre.app/product/41 | BB42: https://drive.google.com/drive/folders/1kl4ymlxIIfzSwWF2aRlGBThiJnQIgsT- | BC42: 2026-07-18-anillo-corona-item-41 | BD42: Legacy + Fotosintesis/Convex + CajaInventario | BE42: costo estimado = precio/2.6 (costo original igualaba al precio)
A43: 42 | B43: 13-nov-2025 | C43: L:A Anillo de Plata | E43: Verde Menta | F43: Plata - comercial | G43: 1 | H43: 7 | K43: Anillo en Plata | L43: 380000 | O43: ASESOR | P43: D.Suárez | Q43: VENDIDA | R43: https://tierramadre.app/p/42 | S43: Fénix | T43: Legalizada | AR43: =IFERROR(VLOOKUP($X43,Lotes!$A:$E,5,FALSE())*$U43,"") | AS43: =IF($L43="","",$L43*2.6) -> 988000 | AU43: 570000 | AV43: 380760 | AW43: 760 | AX43: D.Suarez | AY43: VENDIDO | BA43: https://tierramadre.app/product/42 | BB43: https://drive.google.com/drive/folders/11ijpGxGRddtfSu_TB0ieCZ6ikKCkSdRb | BC43: 2026-07-18-anillo-de-plata-item-42 | BD43: Legacy + Fotosintesis/Convex + CajaInventario | BE43: Caja (snapshot) registra comprador 'D.Suarez' vs asesor actual 'D.Suárez' — revisar si son ventas distintas o la copia está desactualizada.
A44: 43 | B44: 13-nov-2025 | C44: L:A LOTE:23B | E44: Verde Menta | F44: COMERCIAL ESTÁNDAR | G44: 3 | H44: Esmeralda | K44: Lote de Gemas | L44: 85087 | O44: EMBAJADOR | P44: Juan Manuel Escobar Ramirez | Q44: VENDIDA | R44: https://tierramadre.app/p/43 | S44: Fénix | T44: Legalizada | AR44: =IFERROR(VLOOKUP($X44,Lotes!$A:$E,5,FALSE())*$U44,"") | AS44: =IF($L44="","",$L44*2.6) -> 221226.2 | AU44: 221226 | AV44: 221226 | AW44: 0 | AX44: Juan Manuel Escobar Ramirez | AY44: VENDIDO | BA44: https://tierramadre.app/product/43 | BB44: https://drive.google.com/drive/folders/18GBjjbrJ1Z9oyx5MPzA1C8GFinSYqB8C | BC44: 2026-07-18-lote-23b-item-43 | BD44: Legacy + Fotosintesis/Convex + CajaInventario | BE44: costo estimado = precio/2.6 (costo original igualaba al precio)
A45: 44 | B45: 14-nov-2025 | C45: L:A Bombon Super Poderosa | D45: 1.64 | E45: Verde Natural | F45: COMERCIAL SÚPER FINA | G45: 1 | H45: Esmeralda | K45: Gema | L45: 2064615 | O45: ASESOR | P45: M.Gómez | Q45: VENDIDA | R45: https://tierramadre.app/p/44 | S45: Fénix | T45: Legalizada | AR45: =IFERROR(VLOOKUP($X45,Lotes!$A:$E,5,FALSE())*$U45,"") | AS45: =IF($L45="","",$L45*2.6) -> 5367999 | AU45: 5368000 | AV45: 5368000 | AW45: 5368000 | AX45: M.Gomez | AY45: revisar movimiento Bancario con jose -venta Hernando | BA45: https://tierramadre.app/product/44 | BB45: https://drive.google.com/drive/folders/1qcXxmM1O6hqSPq67kPKAC8tuEC0DNur_ | BC45: 2026-07-18-bombon-super-poderosa-item-44 | BD45: Legacy + Fotosintesis/Convex + CajaInventario | BE45: Caja (snapshot) registra comprador 'M.Gomez' vs asesor actual 'M.Gómez' — revisar si son ventas distintas o la copia está desactualizada. · costo estimado = precio/2.6 (costo original igualaba al precio)
A46: 45 | B46: 20-nov-2025 | C46: L:A Diosa Tierra Madre | D46: 1.3 | E46: Verde Vívido | F46: COMERCIAL SÚPER FINA | G46: 1 | H46: Esmeralda | I46: Largo x Ancho | J46: 5.8 × 8.6 mm | K46: Gema | L46: 2046154 | O46: ASESOR | P46: Paola Daza | Q46: VENDIDA | R46: https://tierramadre.app/p/45 | S46: Fénix | T46: Legalizada | AR46: =IFERROR(VLOOKUP($X46,Lotes!$A:$E,5,FALSE())*$U46,"") | AS46: =IF($L46="","",$L46*2.6) -> 5320000.4 | AU46: 5320000 | AV46: 5160400 | AW46: 0 | AX46: Paola Daza | AY46: VENDIDO | BA46: https://tierramadre.app/product/45 | BB46: https://drive.google.com/drive/folders/1ms4-7GKAvUmAzaXZUS04eHtXrkwfaawP | BC46: 2026-07-15-diosa-tierra-madre-item-45 | BD46: Legacy + Fotosintesis/Convex + CajaInventario | BE46: peso ct recuperado de serial Excel · costo estimado = precio/2.6 (costo original igualaba al precio)
A47: 46 | B47: 20-nov-2025 | C47: L:A Amor Platónico | D47: 2.63 | E47: Verde Vívido | F47: COMERCIAL SÚPER FINA | G47: 1 | H47: Cushion | I47: Largo x Ancho | J47: 8.0 × 8.9 mm | K47: Gema | L47: 3679487 | O47: ASESOR | P47: L.A.Ospina | Q47: DISPONIBLE | R47: https://tierramadre.app/p/46 | S47: Fénix | AR47: =IFERROR(VLOOKUP($X47,Lotes!$A:$E,5,FALSE())*$U47,"") | AS47: =IF($L47="","",$L47*2.6) -> 9566666.2 | AU47: 9566667 | AV47: 9566667 | AW47: 0 | AX47: Isa la Negra Vikinga Warrior Portocarrero | AY47: En pago -Gildardo -luis -la negra - fue entregado como prenda por corazón tierra madre | BA47: https://tierramadre.app/product/46 | BB47: https://drive.google.com/drive/folders/1Ft31_79kF2gRHPSTTuzvmdY0WPa2jTv7 | BC47: 2026-07-18-amor-platonico-item-46 | BD47: Legacy + Fotosintesis/Convex + CajaInventario | BE47: Caja (snapshot) registra comprador 'Isa la Negra Vikinga Warrior Portocarrero' vs asesor actual 'L.A.Ospina' — revisar si son ventas distintas o la copia está desactualizada. · costo estimado = precio/2.6 (costo original igualaba al precio)
A48: 47 | B48: 20-nov-2025 | C48: L:A Corazón Tierra Madre | D48: 1.85 | E48: Verde Muzo | F48: FINA ESENCIAL | G48: 1 | H48: Corazón | I48: Largo x Ancho | J48: 7.3 × 8.7 × 5.6 mm | K48: Gema | L48: 10615385 | O48: ASESOR | P48: L.A.Ospina | Q48: VENDIDA | R48: https://tierramadre.app/p/47 | S48: Fénix | T48: Legalizada | AR48: =IFERROR(VLOOKUP($X48,Lotes!$A:$E,5,FALSE())*$U48,"") | AS48: =IF($L48="","",$L48*2.6) -> 27600001 | AU48: 27600000 | AV48: 16698000 | AW48: -2000 | AX48: L.A.Ospina | AY48: Revisar movimiento de Caja esta como egreso | BA48: https://tierramadre.app/product/47 | BB48: https://drive.google.com/drive/folders/1sx6Wv7950TuGZUpca3Au_nQX6O6RY29J | BC48: 2026-07-18-corazon-tierra-madre-item-47 | BD48: Legacy + Fotosintesis/Convex + CajaInventario | BE48: costo estimado = precio/2.6 (costo original igualaba al precio)
A49: 48 | B49: 15-nov-2025 | C49: L:A Anillo Con Dorado | E49: Verde Menta | F49: Plata - comercial | G49: 1 | H49: 6 | K49: Anillo en Plata | L49: 107692 | O49: ASESOR | P49: K.Pineda | Q49: VENDIDA | R49: https://tierramadre.app/p/48 | S49: Fénix | T49: Legalizada | AR49: =IFERROR(VLOOKUP($X49,Lotes!$A:$E,5,FALSE())*$U49,"") | AS49: =IF($L49="","",$L49*2.6) -> 279999.2 | AU49: 280000 | AV49: 280000 | AW49: 0 | AX49: K.Pineda | AY49: VENDIDO | BA49: https://tierramadre.app/product/48 | BB49: https://drive.google.com/drive/folders/1TIPNurw0iSImJgu1D7r4VzDLd_vY_rc_ | BC49: 2026-07-18-anillo-con-dorado-item-48 | BD49: Legacy + Fotosintesis/Convex + CajaInventario | BE49: costo estimado = precio/2.6 (costo original igualaba al precio)
A50: 49 | B50: 23-nov-2025 | C50: L:II-JA Rapunzel | E50: Verde Limón | F50: COMERCIAL FINA | G50: 1 | H50: 7 | K50: Anillo en Plata | L50: 145299 | O50: ASESOR | P50: M.Echeverry | Q50: VENDIDA | R50: https://tierramadre.app/p/49 | S50: Princesas | T50: Legalizada | AR50: =IFERROR(VLOOKUP($X50,Lotes!$A:$E,5,FALSE())*$U50,"") | AS50: =IF($L50="","",$L50*2.6) -> 377777.4 | AU50: 377778 | AV50: 290889.06 | AW50: 0 | AX50: M.Echeverry | AY50: VENDIDO | BA50: https://tierramadre.app/product/49 | BB50: https://drive.google.com/drive/folders/1jQl0Wfw9295nXszrU0gdyHNF403m4jZh | BC50: 2026-07-18-rapunzel-item-49 | BD50: Legacy + Fotosintesis/Convex + CajaInventario | BE50: costo estimado = precio/2.6 (costo original igualaba al precio)
A51: 50 | B51: 23-nov-2025 | C51: L:II-JA Blanca Nieves | E51: Verde Menta | F51: COMERCIAL ESTÁNDAR | G51: 1 | H51: 9 | K51: Anillo en Plata | L51: 130769 | O51: ASESOR | P51: M.Echeverry | Q51: VENDIDA | R51: https://tierramadre.app/p/50 | S51: Princesas | T51: Legalizada | AR51: =IFERROR(VLOOKUP($X51,Lotes!$A:$E,5,FALSE())*$U51,"") | AS51: =IF($L51="","",$L51*2.6) -> 339999.4 | AU51: 340000 | AV51: 261800 | AW51: 0 | AX51: M.Ruiz | AY51: VENDIDO | BA51: https://tierramadre.app/product/50 | BB51: https://drive.google.com/drive/folders/1STVb55Bvaq3y9YZizlz31qsraBo1ZMem | BC51: 2026-07-18-blanca-nieves-item-50 | BD51: Legacy + Fotosintesis/Convex + CajaInventario | BE51: Caja (snapshot) registra comprador 'M.Ruiz' vs asesor actual 'M.Echeverry' — revisar si son ventas distintas o la copia está desactualizada. · costo estimado = precio/2.6 (costo original igualaba al precio)
A52: 51 | B52: 23-nov-2025 | C52: L:II-JA Rapunzel S.F. | E52: Verde Menta | F52: COMERCIAL FINA | G52: 1 | H52: 6 | K52: Anillo en Plata | L52: 145299 | O52: ASESOR | P52: Pablito | Q52: VENDIDA | R52: https://tierramadre.app/p/51 | S52: Princesas | T52: Pte Legalizar | AR52: =IFERROR(VLOOKUP($X52,Lotes!$A:$E,5,FALSE())*$U52,"") | AS52: =IF($L52="","",$L52*2.6) -> 377777.4 | AU52: 377778 | AV52: 377778 | AW52: 207778 | AX52: Pablito | AY52: CARTERA | BA52: https://tierramadre.app/product/51 | BB52: https://drive.google.com/drive/folders/1wFmvI7FZiFX5meLx2B2TLOr-8lRwFlcm | BC52: 2026-07-18-rapunzel-s-f-item-51 | BD52: Legacy + Fotosintesis/Convex + CajaInventario | BE52: costo estimado = precio/2.6 (costo original igualaba al precio)
A53: 52 | B53: 23-nov-2025 | C53: L:II-JA Pocahontas | E53: Verde Menta | F53: COMERCIAL SUPERIOR | G53: 1 | H53: 9 | K53: Anillo en Plata | L53: 130769 | O53: OFI.CALI | P53: M.Campuzano | Q53: DISPONIBLE | R53: https://tierramadre.app/p/52 | S53: Princesas | AR53: =IFERROR(VLOOKUP($X53,Lotes!$A:$E,5,FALSE())*$U53,"") | AS53: =IF($L53="","",$L53*2.6) -> 339999.4 | AU53: 340000 | AV53: 340000 | AW53: 340000 | AX53: Tierra Madre | AY53: Disponible | BA53: https://tierramadre.app/product/52 | BB53: https://drive.google.com/drive/folders/1e0D3pFCJKQI-9CVHAHV6AOLg8Iim1PlR | BC53: 2026-07-18-pocahontas-item-52 | BD53: Legacy + Fotosintesis/Convex + CajaInventario | BE53: Caja (snapshot) registra comprador 'Tierra Madre' vs asesor actual 'M.Campuzano' — revisar si son ventas distintas o la copia está desactualizada. · costo estimado = precio/2.6 (costo original igualaba al precio)
A54: 53 | B54: 23-nov-2025 | C54: L:II-JA Aurora | E54: Verde Menta | F54: COMERCIAL FINA | G54: 1 | H54: 6 | K54: Anillo en Plata | L54: 145299 | O54: ASESOR | P54: D.Suárez | Q54: VENDIDA | R54: https://tierramadre.app/p/53 | S54: Princesas | T54: Legalizada | AR54: =IFERROR(VLOOKUP($X54,Lotes!$A:$E,5,FALSE())*$U54,"") | AS54: =IF($L54="","",$L54*2.6) -> 377777.4 | AU54: 377778 | AV54: 330555.75 | AW54: 0 | AX54: D.Suarez | AY54: VENDIDO | BA54: https://tierramadre.app/product/53 | BB54: https://drive.google.com/drive/folders/1xuml_ZGwUyztBZDUge1WS-9koQJdO003 | BC54: 2026-07-18-aurora-item-53 | BD54: Legacy + Fotosintesis/Convex + CajaInventario | BE54: Caja (snapshot) registra comprador 'D.Suarez' vs asesor actual 'D.Suárez' — revisar si son ventas distintas o la copia está desactualizada. · costo estimado = precio/2.6 (costo original igualaba al precio)
A55: 54 | B55: 23-nov-2025 | C55: L:II-JA Bella | E55: Verde Menta | F55: COMERCIAL SÚPER FINA | G55: 1 | H55: 5 | K55: Anillo en Plata | L55: 163462 | O55: EMBAJADOR | P55: Juan Manuel Escobar Ramirez | Q55: VENDIDA | R55: https://tierramadre.app/p/54 | S55: Princesas | T55: Legalizada | AR55: =IFERROR(VLOOKUP($X55,Lotes!$A:$E,5,FALSE())*$U55,"") | AS55: =IF($L55="","",$L55*2.6) -> 425001.2 | AU55: 425000 | AV55: 425000 | AW55: 0 | AX55: Juan Manuel Escobar Ramirez | AY55: VENDIDO | BA55: https://tierramadre.app/product/54 | BB55: https://drive.google.com/drive/folders/1aGHradCiM_NCjNN6j99-KuqHduR8bcfI | BC55: 2026-07-18-bella-item-54 | BD55: Legacy + Fotosintesis/Convex + CajaInventario | BE55: costo estimado = precio/2.6 (costo original igualaba al precio)
A56: 55 | B56: 23-nov-2025 | C56: L:II-JA Daenerys | E56: Verde Limón | F56: COMERCIAL FINA | G56: 1 | H56: 7 | K56: Anillo en Plata | L56: 163462 | O56: OFI.CALI | P56: D.Suárez | Q56: VENDIDA | R56: https://tierramadre.app/p/55 | S56: Princesas | T56: Legalizada | AR56: =IFERROR(VLOOKUP($X56,Lotes!$A:$E,5,FALSE())*$U56,"") | AS56: =IF($L56="","",$L56*2.6) -> 425001.2 | AU56: 425000 | AV56: 425000 | AW56: 0 | AX56: D.Suarez | AY56: VENDIDO | BA56: https://tierramadre.app/product/55 | BB56: https://drive.google.com/drive/folders/1-7GqjWxrlBr0Hsv9P2_YLS8li6zNbywN | BC56: 2026-07-18-daenerys-item-55 | BD56: Legacy + Fotosintesis/Convex + CajaInventario | BE56: Caja (snapshot) registra comprador 'D.Suarez' vs asesor actual 'D.Suárez' — revisar si son ventas distintas o la copia está desactualizada. · costo estimado = precio/2.6 (costo original igualaba al precio)
A57: 56 | B57: 23-nov-2025 | C57: L:II-JA Anna | E57: Verde Natural | F57: COMERCIAL SÚPER FINA | G57: 1 | H57: 9 | K57: Anillo en Plata | L57: 215385 | O57: EMBAJADOR | P57: Isa la Negra Vikinga Warrior Portocarrero | Q57: VENDIDA | R57: https://tierramadre.app/p/56 | S57: Princesas | T57: Pte Fecha x Legalizar | AR57: =IFERROR(VLOOKUP($X57,Lotes!$A:$E,5,FALSE())*$U57,"") | AS57: =IF($L57="","",$L57*2.6) -> 560001 | AU57: 560000 | AV57: 560000 | AW57: 560000 | AX57: Isa la Negra Vikinga Warrior Portocarrero | AY57: CARTERA | BA57: https://tierramadre.app/product/56 | BB57: https://drive.google.com/drive/folders/16U4f9EorT7PzlJAsdfgrw-q1DvsyqSP1 | BC57: 2026-07-18-anna-item-56 | BD57: Legacy + Fotosintesis/Convex + CajaInventario | BE57: costo estimado = precio/2.6 (costo original igualaba al precio)
A58: 57 | B58: 23-nov-2025 | C58: L:II-JA Policarpa | E58: Verde Menta | F58: COMERCIAL FINA | G58: 1 | H58: 7 | K58: Anillo en Plata | L58: 130769 | O58: ASESOR | P58: O.L.Florez | Q58: VENDIDA | R58: https://tierramadre.app/p/57 | S58: Princesas | T58: Legalizada | AR58: =IFERROR(VLOOKUP($X58,Lotes!$A:$E,5,FALSE())*$U58,"") | AS58: =IF($L58="","",$L58*2.6) -> 339999.4 | AU58: 340000 | AV58: 238000 | AW58: 0 | AX58: L.A.Ospina | AY58: VENDIDO | BA58: https://tierramadre.app/product/57 | BB58: https://drive.google.com/drive/folders/1h_G7E1fRpW83Pxnzsvs5SK_rIWd3vJ50 | BC58: 2026-07-18-policarpa-item-57 | BD58: Legacy + Fotosintesis/Convex + CajaInventario | BE58: Caja (snapshot) registra comprador 'L.A.Ospina' vs asesor actual 'O.L.Florez' — revisar si son ventas distintas o la copia está desactualizada. · costo estimado = precio/2.6 (costo original igualaba al precio)
A59: 58 | B59: 23-nov-2025 | C59: L:II-JA Flora | E59: Verde Limón | F59: COMERCIAL ESTÁNDAR | G59: 1 | H59: 8 | K59: Anillo en Plata | L59: 145299 | O59: ASESOR | P59: O.L.Florez | Q59: VENDIDA | R59: https://tierramadre.app/p/58 | S59: Princesas | T59: Legalizada | AR59: =IFERROR(VLOOKUP($X59,Lotes!$A:$E,5,FALSE())*$U59,"") | AS59: =IF($L59="","",$L59*2.6) -> 377777.4 | AU59: 377778 | AV59: 301089.07 | AW59: 0 | AX59: O.L.Florez | AY59: VENDIDO | BA59: https://tierramadre.app/product/58 | BB59: https://drive.google.com/drive/folders/1ibjVExehN4fC5xb-rQYIunkhU4F42guV | BC59: 2026-07-18-flora-item-58 | BD59: Legacy + Fotosintesis/Convex + CajaInventario | BE59: costo estimado = precio/2.6 (costo original igualaba al precio)
A60: 59 | B60: 23-nov-2025 | C60: L:II-JA Rapunzel II s.p | E60: Verde Menta | F60: COMERCIAL FINA | G60: 1 | H60: 7 | K60: Anillo en Plata | L60: 130769 | O60: EMBAJADOR | P60: Juan Manuel Escobar Ramirez | Q60: VENDIDA | R60: https://tierramadre.app/p/59 | S60: Princesas | T60: Legalizada | AR60: =IFERROR(VLOOKUP($X60,Lotes!$A:$E,5,FALSE())*$U60,"") | AS60: =IF($L60="","",$L60*2.6) -> 339999.4 | AU60: 340000 | AV60: 340000 | AW60: 0 | AX60: Juan Manuel Escobar Ramirez | AY60: VENDIDO | BA60: https://tierramadre.app/product/59 | BB60: https://drive.google.com/drive/folders/1OkVNTPFzW0QoKHa9SseIOFfBqqKtKQeW | BC60: 2026-07-18-rapunzel-ii-s-p-item-59 | BD60: Legacy + Fotosintesis/Convex + CajaInventario | BE60: costo estimado = precio/2.6 (costo original igualaba al precio)
A61: 60 | B61: 23-nov-2025 | C61: L:II-JA Pocahontas II | E61: Verde Limón | F61: COMERCIAL FINA | G61: 1 | H61: 9 | K61: Anillo en Plata | L61: 145299 | O61: OFI.CALI | P61: M.Echeverry | Q61: VENDIDA | R61: https://tierramadre.app/p/60 | S61: Princesas | T61: Legalizada | AR61: =IFERROR(VLOOKUP($X61,Lotes!$A:$E,5,FALSE())*$U61,"") | AS61: =IF($L61="","",$L61*2.6) -> 377777.4 | AU61: 377778 | AV61: 377778 | AW61: 0 | AX61: M.Echeverry | AY61: VENDIDO | BA61: https://tierramadre.app/product/60 | BB61: https://drive.google.com/drive/folders/1gm8ZZYqVTDf8cyxouw50XUTsShYWq3q3 | BC61: 2026-07-18-pocahontas-ii-item-60 | BD61: Legacy + Fotosintesis/Convex + CajaInventario | BE61: costo estimado = precio/2.6 (costo original igualaba al precio)
A62: 61 | B62: 23-nov-2025 | C62: L:II-JA Princesa Azul | E62: Verde Menta | F62: COMERCIAL SUPERIOR | G62: 1 | H62: 7 | K62: Anillo en Plata | L62: 115114 | O62: EMBAJADOR | P62: Isa la Negra Vikinga Warrior Portocarrero | Q62: VENDIDA | R62: https://tierramadre.app/p/61 | S62: Princesas | T62: Legalizada | AR62: =IFERROR(VLOOKUP($X62,Lotes!$A:$E,5,FALSE())*$U62,"") | AS62: =IF($L62="","",$L62*2.6) -> 299296.4 | AU62: 299296 | AV62: 299296 | AW62: 296 | AX62: Mitchel Moreno Marin | AY62: VENDIDO | BA62: https://tierramadre.app/product/61 | BB62: https://drive.google.com/drive/folders/1NsvOFX5VfHoqa4KW4LrrVRd8U6K43NVi | BC62: 2026-07-18-princesa-azul-item-61 | BD62: Legacy + Fotosintesis/Convex + CajaInventario | BE62: Caja (snapshot) registra comprador 'Mitchel Moreno Marin' vs asesor actual 'Isa la Negra Vikinga Warrior Portocarrero' — revisar si son ventas distintas o la copia está desactualizada. · costo estimado = precio/2.6 (costo original igualaba al precio)
A63: 62 | B63: 23-nov-2025 | C63: L:II-JA La Reina Margot | E63: Verde Limón | F63: COMERCIAL SUPERIOR | G63: 1 | H63: 9 | K63: Anillo en Plata | L63: 215385 | O63: EMBAJADOR | P63: Isa la Negra Vikinga Warrior Portocarrero | Q63: VENDIDA | R63: https://tierramadre.app/p/62 | S63: Princesas | T63: Pte Fecha x Legalizar | AR63: =IFERROR(VLOOKUP($X63,Lotes!$A:$E,5,FALSE())*$U63,"") | AS63: =IF($L63="","",$L63*2.6) -> 560001 | AU63: 560000 | AV63: 560000 | AW63: 560000 | AX63: Isa la Negra Vikinga Warrior Portocarrero | AY63: CARTERA | BA63: https://tierramadre.app/product/62 | BB63: https://drive.google.com/drive/folders/1b-bUsX_n_-bW6pE_oZyT4D1xIKXKQCtI | BC63: 2026-07-18-la-reina-margot-item-62 | BD63: Legacy + Fotosintesis/Convex + CajaInventario | BE63: costo estimado = precio/2.6 (costo original igualaba al precio)
A64: 63 | B64: 23-nov-2025 | C64: L:II-JA La Reina Isabell | E64: Verde Menta | F64: COMERCIAL SUPERIOR | G64: 1 | H64: 8 | K64: Anillo en Plata | L64: 239316 | O64: ASESOR | P64: O.L.Florez | Q64: VENDIDA | R64: https://tierramadre.app/p/63 | S64: Princesas | T64: Pte Fecha x Legalizar | AR64: =IFERROR(VLOOKUP($X64,Lotes!$A:$E,5,FALSE())*$U64,"") | AS64: =IF($L64="","",$L64*2.6) -> 622221.6 | AU64: 622222 | AV64: 622222 | AW64: 375222 | AX64: O.L.Florez | AY64: CARTERA | BA64: https://tierramadre.app/product/63 | BB64: https://drive.google.com/drive/folders/1KdcYpT8nXZ0JPYTAlmQniQn35JLYJMJu | BC64: 2026-07-18-la-reina-isabell-item-63 | BD64: Legacy + Fotosintesis/Convex + CajaInventario | BE64: costo estimado = precio/2.6 (costo original igualaba al precio)
A65: 64 | B65: 23-nov-2025 | C65: L:II-JA Gota del Pacifico | D65: 18 | E65: Verde Muzo | F65: FINA ESENCIAL | G65: 1 | H65: 7 | K65: Anillo en Oro | L65: 1282051 | O65: ASESOR | P65: M.Ruiz | Q65: Retornado | R65: https://tierramadre.app/p/64 | S65: Princesas | AR65: =IFERROR(VLOOKUP($X65,Lotes!$A:$E,5,FALSE())*$U65,"") | AS65: =IF($L65="","",$L65*2.6) -> 3333332.6 | AU65: 3333333 | AV65: 3333333 | AW65: 0 | AX65: M.Ruiz | AY65: RETORNADO | BA65: https://tierramadre.app/product/64 | BB65: https://drive.google.com/drive/folders/1IF9RnKU3s95Dnh3YrRDBDiTRAQmQayMN | BC65: 2026-07-18-gota-del-pacifico-item-64 | BD65: Legacy + Fotosintesis/Convex + CajaInventario | BE65: costo estimado = precio/2.6 (costo original igualaba al precio)
A66: 65 | B66: 23-nov-2025 | C66: L:II-JA Raíz de Gaia | D66: 18 | E66: Verde Muzo | F66: FINA ESENCIAL | G66: 1 | H66: 8 | K66: Anillo en Oro | L66: 1373627 | O66: ASESOR | P66: M.Ruiz | Q66: Retornado | R66: https://tierramadre.app/p/65 | S66: Princesas | AR66: =IFERROR(VLOOKUP($X66,Lotes!$A:$E,5,FALSE())*$U66,"") | AS66: =IF($L66="","",$L66*2.6) -> 3571430.2 | AU66: 3571429 | AV66: 3571429 | AW66: 0 | AX66: M.Ruiz | AY66: RETORNADO | BA66: https://tierramadre.app/product/65 | BB66: https://drive.google.com/drive/folders/1WI5yPcIgb8TIUppJdGY3co_PBt8yRbjB | BC66: 2026-07-18-raiz-de-gaia-item-65 | BD66: Legacy + Fotosintesis/Convex + CajaInventario | BE66: costo estimado = precio/2.6 (costo original igualaba al precio)
A67: 66 | B67: 23-nov-2025 | C67: L:A-23F Espejo Sagrado | D67: 0.48 | E67: Verde Limón | F67: COMERCIAL SÚPER FINA | G67: 1 | H67: Esmeralda | I67: Largo x Ancho | J67: 4.2 × 5.1 mm | K67: Gema | L67: 180473 | O67: ASESOR | P67: K.Pineda | Q67: VENDIDA | R67: https://tierramadre.app/p/66 | S67: Fénix | T67: Legalizada | AR67: =IFERROR(VLOOKUP($X67,Lotes!$A:$E,5,FALSE())*$U67,"") | AS67: =IF($L67="","",$L67*2.6) -> 469229.8 | AU67: 469231 | AV67: 469231 | AW67: 0 | AX67: K.Pineda | AY67: VENDIDO | BA67: https://tierramadre.app/product/66 | BB67: https://drive.google.com/drive/folders/16ECdPjmUJwjenK4B0cjvj_fHI6keMnK1 | BC67: 2026-07-18-espejo-sagrado-item-66 | BD67: Legacy + Fotosintesis/Convex + CajaInventario | BE67: costo estimado = precio/2.6 (costo original igualaba al precio)
A68: 67 | B68: 23-nov-2025 | C68: L:A-23F Hércules | D68: 0.7 | E68: Verde Limón | F68: COMERCIAL SÚPER FINA | G68: 1 | H68: Esmeralda | I68: Largo x Ancho | J68: 5.8 × 4.5 mm | K68: Gema | L68: 170812 | O68: ASESOR | P68: K.Pineda | Q68: VENDIDA | R68: https://tierramadre.app/p/67 | S68: Fénix | T68: Legalizada | AR68: =IFERROR(VLOOKUP($X68,Lotes!$A:$E,5,FALSE())*$U68,"") | AS68: =IF($L68="","",$L68*2.6) -> 444111.2 | AU68: 444112 | AV68: 444112 | AW68: 0 | AX68: K.Pineda | AY68: VENDIDO | BA68: https://tierramadre.app/product/67 | BB68: https://drive.google.com/drive/folders/1R3gRuekRJVfWqyNWTLYHCrLnPt6bS8SD | BC68: 2026-07-18-hercules-item-67 | BD68: Legacy + Fotosintesis/Convex + CajaInventario | BE68: costo estimado = precio/2.6 (costo original igualaba al precio)
A69: 68 | B69: 23-nov-2025 | C69: L:A-23F Adán y Eva | D69: 0.95 | E69: Verde Limón | F69: COMERCIAL SÚPER FINA | G69: 2 | H69: Esmeralda | I69: Largo x Ancho | J69: 4.4 × 5.0 mm | K69: Gema | L69: 117308 | O69: ASESOR | P69: Pablito | Q69: VENDIDA | R69: https://tierramadre.app/p/68 | S69: Fénix | T69: Legalizada | AR69: =IFERROR(VLOOKUP($X69,Lotes!$A:$E,5,FALSE())*$U69,"") | AS69: =IF($L69="","",$L69*2.6) -> 305000.8 | AU69: 305000 | AV69: 305000 | AW69: 61000 | AX69: Pablito | AY69: VENDIDO | BA69: https://tierramadre.app/product/68 | BB69: https://drive.google.com/drive/folders/1A3aE4pv1DSNfbt7HPZ3IvFDltZLFMCfD | BC69: 2026-07-18-adan-y-eva-item-68 | BD69: Legacy + Fotosintesis/Convex + CajaInventario | BE69: costo estimado = precio/2.6 (costo original igualaba al precio)
A70: 69 | B70: 23-nov-2025 | C70: L:A-105 Chispa Divina | D70: 0.89 | E70: Verde Limón | F70: COMERCIAL FINA | G70: 1 | H70: Esmeralda | I70: Largo x Ancho | J70: 5.6 × 7.0 mm | K70: Gema | L70: 126923 | O70: ASESOR | P70: M.Echeverry | Q70: VENDIDA | R70: https://tierramadre.app/p/69 | S70: Fénix | T70: Legalizada | AR70: =IFERROR(VLOOKUP($X70,Lotes!$A:$E,5,FALSE())*$U70,"") | AS70: =IF($L70="","",$L70*2.6) -> 329999.8 | AU70: 330000 | AV70: 330000 | AW70: 0 | AX70: M.Echeverry | AY70: VENDIDO | BA70: https://tierramadre.app/product/69 | BB70: https://drive.google.com/drive/folders/1Gtl75Pe-hBS5rGzF5Nopv3FJl4Yyu25G | BC70: 2026-07-15-chispa-divina-item-69 | BD70: Legacy + Fotosintesis/Convex + CajaInventario | BE70: costo estimado = precio/2.6 (costo original igualaba al precio)
A71: 70 | B71: 23-nov-2025 | C71: L:A-105 Apolo | D71: 1.29 | E71: Verde Limón | F71: COMERCIAL SUPERIOR | G71: 1 | H71: Esmeralda | I71: Largo x Ancho | J71: 5.4 × 8.1 mm | K71: Gema | L71: 483750 | O71: EMBAJADOR | P71: Juan Manuel Escobar Ramirez | Q71: VENDIDA | R71: https://tierramadre.app/p/70 | S71: Fénix | T71: Legalizada | AR71: =IFERROR(VLOOKUP($X71,Lotes!$A:$E,5,FALSE())*$U71,"") | AS71: =IF($L71="","",$L71*2.6) -> 1257750 | AU71: 725625 | AV71: 725625 | AW71: 0 | AX71: Juan Manuel Escobar Ramirez | AY71: VENDIDO | BA71: https://tierramadre.app/product/70 | BB71: https://drive.google.com/drive/folders/1L_YfKwQiYXVfcThgHnc4z_5qOh32BVKO | BC71: 2026-07-15-apolo-item-70 | BD71: Legacy + Fotosintesis/Convex + CajaInventario
A72: 71 | B72: 23-nov-2025 | C72: L:A-105 Firmamento | D72: 0.47 | E72: Verde Limón | F72: COMERCIAL FINA | G72: 1 | H72: Esmeralda | I72: Largo x Ancho | J72: 4.2 × 6.2 mm | K72: Gema | L72: 176250 | O72: ASESOR | P72: M.Campuzano | Q72: VENDIDA | R72: https://tierramadre.app/p/71 | S72: Fénix | T72: Legalizada | AR72: =IFERROR(VLOOKUP($X72,Lotes!$A:$E,5,FALSE())*$U72,"") | AS72: =IF($L72="","",$L72*2.6) -> 458250 | AU72: 264375 | AV72: 211235.62 | AW72: 235.625 | AX72: M.Campuzano | AY72: VENDIDO | BA72: https://tierramadre.app/product/71 | BB72: https://drive.google.com/drive/folders/1DuCtKJmwoJTA_LAY6Kzd__hZZOsAMRFd | BC72: 2026-07-18-firmamento-item-71 | BD72: Legacy + Fotosintesis/Convex + CajaInventario
A73: 72 | B73: 23-nov-2025 | C73: L:A-105 Troya | D73: 0.81 | E73: Verde Limón | F73: COMERCIAL FINA | G73: 1 | H73: Esmeralda | I73: Largo x Ancho | J73: 5.2 × 7.3 mm | K73: Gema | L73: 306000 | O73: ASESOR | P73: M.Echeverry | Q73: VENDIDA | R73: https://tierramadre.app/p/72 | S73: Fénix | T73: Legalizada | AR73: =IFERROR(VLOOKUP($X73,Lotes!$A:$E,5,FALSE())*$U73,"") | AS73: =IF($L73="","",$L73*2.6) -> 795600 | AU73: 397800 | AV73: 397800 | AW73: 0 | AX73: M.Echeverry | AY73: VENDIDO | BA73: https://tierramadre.app/product/72 | BB73: https://drive.google.com/drive/folders/19KUtfuTEdk2Kni4fI1jqlZFIXr3FQZMT | BC73: 2026-07-15-troya-item-72 | BD73: Legacy + Fotosintesis/Convex + CajaInventario
A74: 73 | B74: 23-nov-2025 | C74: L:A-105 Ventana al cielo | D74: 0.7 | E74: Verde Limón | F74: COMERCIAL SUPERIOR | G74: 1 | H74: Esmeralda | I74: Largo x Ancho | J74: 4.7 × 5.8 mm | K74: Gema | L74: 262500 | O74: ASESOR | P74: M.Campuzano | Q74: VENDIDA | R74: https://tierramadre.app/p/73 | S74: Fénix | T74: Pte Fecha x Legalizar | AR74: =IFERROR(VLOOKUP($X74,Lotes!$A:$E,5,FALSE())*$U74,"") | AS74: =IF($L74="","",$L74*2.6) -> 682500 | AU74: 328125 | AV74: 328125 | AW74: 328125 | AX74: M.Campuzano | AY74: CARTERA | BA74: https://tierramadre.app/product/73 | BB74: https://drive.google.com/drive/folders/1P0aXu-Titkf1-oHW_x4tZGNx_YiCMeez | BC74: 2026-07-18-ventana-al-cielo-item-73 | BD74: Legacy + Fotosintesis/Convex + CajaInventario
A75: 74 | B75: 23-nov-2025 | C75: L:A-105 Fuego | D75: 0.7 | E75: Verde Limón | F75: COMERCIAL ESTÁNDAR | G75: 1 | H75: Esmeralda | I75: Largo x Ancho | J75: 4.7 × 6.1 mm | K75: Gema | L75: 250000 | O75: ASESOR | P75: M.Campuzano | Q75: VENDIDA | R75: https://tierramadre.app/p/74 | S75: Fénix | T75: Legalizada | AR75: =IFERROR(VLOOKUP($X75,Lotes!$A:$E,5,FALSE())*$U75,"") | AS75: =IF($L75="","",$L75*2.6) -> 650000 | AU75: 295000 | AV75: 295000 | AW75: 0 | AX75: M.Campuzano | AY75: VENDIDO | BA75: https://tierramadre.app/product/74 | BB75: https://drive.google.com/drive/folders/18wnpB7vVAqf07HdGJohp-CvzEI8HT6Yd | BC75: 2026-07-18-fuego-item-74 | BD75: Legacy + Fotosintesis/Convex + CajaInventario
A76: 75 | B76: 24-nov-2025 | C76: L:A-104 Aria | D76: 0.32 | E76: Verde Limón | F76: COMERCIAL ESTÁNDAR | G76: 1 | H76: Ovalo | I76: Largo x Ancho | J76: 4.8 × 3.9 mm | K76: Gema | L76: 226000 | O76: ASESOR | P76: Isa la Negra Vikinga Warrior Portocarrero | Q76: DISPONIBLE | R76: https://tierramadre.app/p/75 | S76: Fénix | AR76: =IFERROR(VLOOKUP($X76,Lotes!$A:$E,5,FALSE())*$U76,"") | AS76: =IF($L76="","",$L76*2.6) -> 587600 | AU76: 293800 | AV76: 293800 | AW76: 293800 | AX76: Isa la Negra Vikinga Warrior Portocarrero | AY76: PRODUCCION | BA76: https://tierramadre.app/product/75 | BB76: https://drive.google.com/drive/folders/1sx0ohUbliPkeeK-lAXu3WQWHgd40euCk | BC76: 2026-07-18-aria-item-75 | BD76: Legacy + Fotosintesis/Convex + CajaInventario
A77: 76 | B77: 24-nov-2025 | C77: L:A-104 Ojos del Universo | D77: 0.78 | E77: Verde Limón | F77: COMERCIAL SUPERIOR | G77: 2 | H77: Ovalo | I77: Largo x Ancho | J77: 4.7 × 3.2 mm | K77: Gema | L77: 236000 | O77: OFI.CALI | P77: M.Campuzano | Q77: DISPONIBLE | R77: https://tierramadre.app/p/76 | S77: Fénix | X77: C-050 | AF77: Gema Facetada | AQ77: 0.59 | AR77: =IFERROR(VLOOKUP($X77,Lotes!$A:$E,5,FALSE())*$U77,"") -> 0 | AS77: =IF($L77="","",$L77*2.6) -> 613600 | AU77: 823500 | AV77: 823500 | AW77: 823500 | AX77: Tierra Madre | AY77: Disponible | BA77: https://tierramadre.app/product/76 | BB77: https://drive.google.com/drive/folders/1lYMKrxQkMjB85iTUUoV-ePDDj_WLQ6dm | BC77: 2026-07-10-ojos-del-universo-item-76 | BD77: Legacy + Fotosintesis/Convex + ModeloPrecios + CajaInventario | BE77: Calidad difiere: legacy=Comercial Superior vs modeloPrecios=Fina esencial | Caja (snapshot) registra comprador 'Tierra Madre' vs asesor actual 'M.Campuzano' — revisar si son ventas distintas o la copia está desactualizada.
A78: 77 | B78: 24-nov-2025 | C78: L:A-104 Dos Pequitas | D78: 0.47 | E78: Verde Limón | F78: COMERCIAL FINA | G78: 2 | H78: Ovalo | I78: Largo x Ancho | J78: 4.3 × 3.2 mm | K78: Gema | L78: 156000 | O78: OFI.CALI | P78: M.Campuzano | Q78: DISPONIBLE | R78: https://tierramadre.app/p/77 | S78: Fénix | X78: C-051 | AF78: Gema Facetada | AQ78: 0.55 | AR78: =IFERROR(VLOOKUP($X78,Lotes!$A:$E,5,FALSE())*$U78,"") -> 0 | AS78: =IF($L78="","",$L78*2.6) -> 405600 | AU78: 486000 | AV78: 486000 | AW78: 486000 | AX78: Tierra Madre | AY78: Disponible | BA78: https://tierramadre.app/product/77 | BB78: https://drive.google.com/drive/folders/10c8xFpiKVOgiAad2NNaCXisnHP4sq85H | BC78: 2026-07-10-dos-pequitas-item-77 | BD78: Legacy + Fotosintesis/Convex + ModeloPrecios + CajaInventario | BE78: Calidad difiere: legacy=Comercial Fina vs modeloPrecios=C. Superior | Caja (snapshot) registra comprador 'Tierra Madre' vs asesor actual 'M.Campuzano' — revisar si son ventas distintas o la copia está desactualizada.
A79: 78 | B79: 24-nov-2025 | C79: L:A-104 Cleopatra | D79: 0.28 | E79: Verde Limón | F79: COMERCIAL FINA | G79: 1 | H79: Ovalo | I79: Largo x Ancho | J79: 3.8 × 4.7 mm | K79: Gema | L79: 76154 | O79: ASESOR | P79: M.Echeverry | Q79: VENDIDA | R79: https://tierramadre.app/p/78 | S79: Fénix | T79: Legalizada | AR79: =IFERROR(VLOOKUP($X79,Lotes!$A:$E,5,FALSE())*$U79,"") | AS79: =IF($L79="","",$L79*2.6) -> 198000.4 | AU79: 198000 | AV79: 198000 | AW79: 0 | AX79: M.Echeverry | AY79: VENDIDO | BA79: https://tierramadre.app/product/78 | BB79: https://drive.google.com/drive/folders/1mn1TtmDp2c-PJesTEAvMiF1YpSYiwZHm | BC79: 2026-07-18-cleopatra-item-78 | BD79: Legacy + Fotosintesis/Convex + CajaInventario | BE79: costo estimado = precio/2.6 (costo original igualaba al precio)
A80: 79 | B80: 24-nov-2025 | C80: L:A-104 Ojo de Afrodita | D80: 0.54 | E80: Verde Limón | F80: COMERCIAL SUPERIOR | G80: 1 | H80: Ovalo | I80: Largo x Ancho | J80: 4.5 × 5.5 mm | K80: Gema | L80: 146923 | O80: ASESOR | P80: Juan Manuel Escobar Ramirez | R80: https://tierramadre.app/p/79 | S80: Fénix | AR80: =IFERROR(VLOOKUP($X80,Lotes!$A:$E,5,FALSE())*$U80,"") | AS80: =IF($L80="","",$L80*2.6) -> 381999.8 | AU80: 382000 | AV80: 382000 | AW80: 382000 | AX80: Juan Manuel Escobar Ramirez | AY80: PRODUCCION | BA80: https://tierramadre.app/product/79 | BB80: https://drive.google.com/drive/folders/1CF9sC4eS6i44wgl9CwNTB8LW74FPzI7D | BC80: 2026-07-18-ojo-de-afrodita-item-79 | BD80: Legacy + Fotosintesis/Convex + CajaInventario | BE80: costo estimado = precio/2.6 (costo original igualaba al precio)
A81: 80 | B81: 24-nov-2025 | C81: L:A-104 Grecia | D81: 0.7 | E81: Verde Limón | F81: COMERCIAL SUPERIOR | G81: 1 | H81: Ovalo | I81: Largo x Ancho | J81: 6.2 × 4.8 mm | K81: Gema | L81: 213576 | O81: OFI.CALI | P81: M.Campuzano | Q81: DISPONIBLE | R81: https://tierramadre.app/p/80 | S81: Fénix | X81: C-053 | AF81: Gema Facetada | AQ81: 1.3 | AR81: =IFERROR(VLOOKUP($X81,Lotes!$A:$E,5,FALSE())*$U81,"") -> 0 | AS81: =IF($L81="","",$L81*2.6) -> 555297.6 | AU81: 519200 | AV81: 519200 | AW81: 519200 | AX81: Tierra Madre | AY81: Disponible | BA81: https://tierramadre.app/product/80 | BB81: https://drive.google.com/drive/folders/1fN4g_gZX_vwsq3zshJozHnuUvhhqB4vf | BC81: 2026-07-10-grecia-item-80 | BD81: Legacy + Fotosintesis/Convex + ModeloPrecios + CajaInventario | BE81: Calidad difiere: legacy=COMERCIAL SUPERIOR vs modeloPrecios=C. Estándar | Caja (snapshot) registra comprador 'Tierra Madre' vs asesor actual 'M.Campuzano' — revisar si son ventas distintas o la copia está desactualizada.
A82: 81 | B82: 24-nov-2025 | C82: L:A-104 Lalala | D82: 0.84 | E82: Verde Menta | F82: COMERCIAL FINA | G82: 1 | H82: Ovalo | I82: Largo x Ancho | J82: 5.1 × 8.0 mm | K82: Gema | L82: 580000 | O82: OFI.CALI | P82: Isa la Negra Vikinga Warrior Portocarrero | Q82: VENDIDA | R82: https://tierramadre.app/p/81 | S82: Fénix | AR82: =IFERROR(VLOOKUP($X82,Lotes!$A:$E,5,FALSE())*$U82,"") | AS82: =IF($L82="","",$L82*2.6) -> 1508000 | AU82: 870000 | AV82: 870000 | AW82: 0 | AX82: Tierra Madre | AY82: En Aporte Actividad campamento | BA82: https://tierramadre.app/product/81 | BB82: https://drive.google.com/drive/folders/1fZDKeCj6H2CV33cwdKxgc-5DqB12UlYX | BC82: 2026-07-18-l-a-104-lalala-item-81 | BD82: Legacy + Fotosintesis/Convex + CajaInventario | BE82: Caja (snapshot) registra comprador 'Tierra Madre' vs asesor actual 'Isa la Negra Vikinga Warrior Portocarrero' — revisar si son ventas distintas o la copia está desactualizada.
A83: 82 | B83: 24-nov-2025 | C83: La Diva | D83: 0.15 | E83: Verde Natural | F83: COMERCIAL FINA | G83: 1 | H83: Redonda | I83: Diámetro | J83: 35 mm | K83: Gema | L83: 44231 | O83: ASESOR | P83: M.Gómez | Q83: VENDIDA | R83: https://tierramadre.app/p/82 | S83: Fénix | T83: Legalizada | AR83: =IFERROR(VLOOKUP($X83,Lotes!$A:$E,5,FALSE())*$U83,"") | AS83: =IF($L83="","",$L83*2.6) -> 115000.6 | AU83: 115000 | AV83: 92000 | AW83: 0 | AX83: M.Gomez | AY83: VENDIDO | BA83: https://tierramadre.app/product/82 | BB83: https://drive.google.com/drive/folders/1xovP-m98wkPYrMrzecIKey8vQhNcJ3xd | BC83: 2026-07-18-la-diva-item-82 | BD83: Legacy + Fotosintesis/Convex + CajaInventario | BE83: Caja (snapshot) registra comprador 'M.Gomez' vs asesor actual 'M.Gómez' — revisar si son ventas distintas o la copia está desactualizada. · costo estimado = precio/2.6 (costo original igualaba al precio)
A84: 83 | B84: 24-nov-2025 | C84: Dos Luceritos | D84: 0.12 | E84: Verde Menta | F84: COMERCIAL FINA | G84: 2 | H84: Redonda | I84: Diámetro | J84: 27 mm | K84: Gema | L84: 92500 | O84: ASESOR | P84: M.Gómez | Q84: VENDIDA | R84: https://tierramadre.app/p/83 | S84: Fénix | T84: Legalizada | AR84: =IFERROR(VLOOKUP($X84,Lotes!$A:$E,5,FALSE())*$U84,"") | AS84: =IF($L84="","",$L84*2.6) -> 240500 | AU84: 138750 | AV84: 92546.25 | AW84: 46.25 | AX84: M.Gomez | AY84: VENDIDO | BA84: https://tierramadre.app/product/83 | BB84: https://drive.google.com/drive/folders/1ltHSxwZsYrpy69sA_NHG0Q-oZlnO9GiV | BC84: 2026-07-18-dos-luceritos-item-83 | BD84: Legacy + Fotosintesis/Convex + CajaInventario | BE84: Caja (snapshot) registra comprador 'M.Gomez' vs asesor actual 'M.Gómez' — revisar si son ventas distintas o la copia está desactualizada.
A85: 84 | B85: 24-nov-2025 | C85: Instante Perfecto | D85: 0.16 | E85: Verde Limón | F85: COMERCIAL FINA | G85: 1 | H85: Redonda | I85: Diámetro | J85: 3.3 mm | K85: Gema | L85: 122500 | O85: ASESOR | P85: Pablito | Q85: VENDIDA | R85: https://tierramadre.app/p/84 | S85: Fénix | T85: Pte Fecha x Legalizar | AR85: =IFERROR(VLOOKUP($X85,Lotes!$A:$E,5,FALSE())*$U85,"") | AS85: =IF($L85="","",$L85*2.6) -> 318500 | AU85: 183750 | AV85: 183750 | AW85: 183750 | AX85: Pablito | AY85: CARTERA | BA85: https://tierramadre.app/product/84 | BB85: https://drive.google.com/drive/folders/1bpldswg2AQgcXcelcLENFGmQu14vLirT | BC85: 2026-07-18-instante-perfecto-item-84 | BD85: Legacy + Fotosintesis/Convex + CajaInventario
A86: 85 | B86: 24-nov-2025 | C86: Viento del Pacifico | D86: 0.22 | E86: Verde Menta | F86: COMERCIAL FINA | G86: 1 | H86: Redonda | I86: Diámetro | J86: 4.1 mm | K86: Gema | L86: 51846 | O86: OFI.CALI | P86: Jennifer.Florez | Q86: VENDIDA | R86: https://tierramadre.app/p/85 | S86: Fénix | T86: Legalizada | AR86: =IFERROR(VLOOKUP($X86,Lotes!$A:$E,5,FALSE())*$U86,"") | AS86: =IF($L86="","",$L86*2.6) -> 134799.6 | AU86: 134800 | AV86: 134800 | AW86: 0 | AX86: Jenifer.Florez | AY86: VENDIDO | BA86: https://tierramadre.app/product/85 | BB86: https://drive.google.com/drive/folders/1xhyrTI866_-nQxYhKxaGsrL6mqYi8ODz | BC86: 2026-07-18-viento-del-pacifico-item-85 | BD86: Legacy + Fotosintesis/Convex + CajaInventario | BE86: Caja (snapshot) registra comprador 'Jenifer.Florez' vs asesor actual 'Jennifer.Florez' — revisar si son ventas distintas o la copia está desactualizada. · costo estimado = precio/2.6 (costo original igualaba al precio)
A87: 86 | B87: 08-dic-2025 | C87: Estrellas del Amanecer | D87: 0.55 | E87: Verde Limón | F87: COMERCIAL FINA | G87: 2 | H87: Redonda | K87: Gema | L87: 288736 | O87: ASESOR | P87: Paola Daza | Q87: VENDIDA | R87: https://tierramadre.app/p/86 | S87: Secretos del Bosque | T87: Legalizada | AR87: =IFERROR(VLOOKUP($X87,Lotes!$A:$E,5,FALSE())*$U87,"") | AS87: =IF($L87="","",$L87*2.6) -> 750713.6 | AU87: 650000 | AV87: 630500 | AW87: 0 | AX87: Paola Daza | AY87: VENDIDO | BA87: https://tierramadre.app/product/86 | BB87: https://drive.google.com/drive/folders/1LJOAVAR6Pa_iIpz0Lpzo7w1iG4-wY0yh | BC87: 2026-07-18-estrellas-del-amanecer-item-86 | BD87: Legacy + Fotosintesis/Convex + CajaInventario
A88: 87 | B88: 08-dic-2025 | C88: Hermanas de la luna | D88: 1.43 | E88: Verde Limón | F88: COMERCIAL FINA | G88: 2 | H88: Redonda | I88: Diámetro | J88: 6 mm | K88: Gema | L88: 737308 | O88: OFI.CALI | P88: Alvaro Pelaez | Q88: VENDIDA | R88: https://tierramadre.app/p/87 | S88: Fénix | T88: Legalizada | AR88: =IFERROR(VLOOKUP($X88,Lotes!$A:$E,5,FALSE())*$U88,"") | AS88: =IF($L88="","",$L88*2.6) -> 1917000.8 | AU88: 2654000 | AV88: 1900264 | AW88: 0 | AX88: Alvaro Pelaez | AY88: VENDIDO | BA88: https://tierramadre.app/product/87 | BB88: https://drive.google.com/drive/folders/1ySmcjonlfQjzrQi2NnOBbx8D-sXIz2R_ | BC88: 2026-07-18-hermanas-de-la-luna-item-87 | BD88: Legacy + Fotosintesis/Convex + Ventas + CajaInventario
A89: 88 | B89: 08-dic-2025 | C89: Misterio Profundo | D89: 2.11 | E89: Verde Natural | F89: COMERCIAL FINA | G89: 1 | H89: Ovalo | I89: Largo x Ancho | J89: 9.5 × 7.2 × 5.1 mm | K89: Gema | L89: 334000 | O89: OFI.CALI | P89: M.Campuzano | Q89: DISPONIBLE | R89: https://tierramadre.app/p/88 | S89: Fénix | X89: C-044 | AF89: Gema Facetada | AR89: =IFERROR(VLOOKUP($X89,Lotes!$A:$E,5,FALSE())*$U89,"") -> 0 | AS89: =IF($L89="","",$L89*2.6) -> 868400 | AU89: 3698914 | AV89: 3698914 | AW89: 3698914 | AX89: Tierra Madre | AY89: Disponible | BA89: https://tierramadre.app/product/88 | BB89: https://drive.google.com/drive/folders/1_sXi1AcPSxRu45xUVuPK_IgoqjT1_W0N | BC89: 2026-07-13-misterio-profundo-item-88 | BD89: Legacy + Fotosintesis/Convex + ModeloPrecios + CajaInventario | BE89: peso ct recuperado de serial Excel · Calidad difiere: legacy=Comercial Fina vs modeloPrecios=C. Fina | Caja (snapshot) registra comprador 'Tierra Madre' vs asesor actual 'M.Campuzano' — revisar si son ventas distintas o la copia está desactualizada. · revisar: costo << precio (posible error de escala ×1000)
A90: 89 | B90: 08-dic-2025 | C90: Hadas del Bosque | D90: 0.7 | E90: Verde Limón | F90: COMERCIAL FINA | G90: 2 | H90: Esmeralda | I90: Largo x Ancho | J90: 5.2 -3.2 5.0-3.4 mm | K90: Gema | L90: 140300 | O90: OFI.CALI | P90: M.Campuzano | Q90: DISPONIBLE | R90: https://tierramadre.app/p/89 | S90: Secretos del Bosque | X90: C-046 | AF90: Gema Facetada | AR90: =IFERROR(VLOOKUP($X90,Lotes!$A:$E,5,FALSE())*$U90,"") -> 0 | AS90: =IF($L90="","",$L90*2.6) -> 364780 | AU90: 830116 | AV90: 830116 | AW90: 830116 | AX90: Tierra Madre | AY90: Disponible | BA90: https://tierramadre.app/product/89 | BB90: https://drive.google.com/drive/folders/15u_SMCSkcmpEIXmljw7dLaA5imYXecKp | BC90: 2026-07-18-hadas-del-bosque-item-89 | BD90: Legacy + Fotosintesis/Convex + ModeloPrecios + CajaInventario | BE90: Calidad difiere: legacy=Comercial Fina vs modeloPrecios=C. Super Fina | Caja (snapshot) registra comprador 'Tierra Madre' vs asesor actual 'M.Campuzano' — revisar si son ventas distintas o la copia está desactualizada.
A91: 90 | B91: 08-dic-2025 | C91: Quinto Elemento | D91: 0.23 | E91: Verde Vívido | F91: FINA SUBLIME | G91: 1 | H91: Baguette | K91: Gema | L91: 207207 | O91: ASESOR | P91: Paola Daza | Q91: VENDIDA | R91: https://tierramadre.app/p/90 | S91: Secretos del Bosque | T91: Legalizada | AR91: =IFERROR(VLOOKUP($X91,Lotes!$A:$E,5,FALSE())*$U91,"") | AS91: =IF($L91="","",$L91*2.6) -> 538738.2 | AU91: 850000 | AV91: 824500 | AW91: 0 | AX91: Paola Daza | AY91: VENDIDO | BA91: https://tierramadre.app/product/90 | BB91: https://drive.google.com/drive/folders/19vFhLC4i6NPztkyaomjvA9EFZRC0NPy8 | BC91: 2026-07-18-quinto-elemento-item-90 | BD91: Legacy + Fotosintesis/Convex + CajaInventario
A92: 91 | B92: 08-dic-2025 | C92: Viento Nocturno | D92: 0.95 | E92: Verde Natural | F92: COMERCIAL SUPERIOR | G92: 1 | H92: Lágrima | I92: Largo x Ancho | J92: 9.5 × 5.4 × 3.8 mm | K92: Gema | L92: 120000 | O92: ASESOR | P92: M.Campuzano | Q92: VENDIDA | R92: https://tierramadre.app/p/91 | S92: Secretos del Bosque | T92: Pte Fecha x Legalizar | X92: C-060 | AF92: Gola | AR92: =IFERROR(VLOOKUP($X92,Lotes!$A:$E,5,FALSE())*$U92,"") -> 0 | AS92: =IF($L92="","",$L92*2.6) -> 312000 | AU92: 288000 | AV92: 288000 | AW92: 288000 | AX92: M.Campuzano | AY92: CARTERA | BA92: https://tierramadre.app/product/91 | BB92: https://drive.google.com/drive/folders/1ptbNaCnhb3s5wLBUuCMuTB86OKZDCqJd | BC92: 2026-07-13-viento-nocturno-item-91 | BD92: Legacy + Fotosintesis/Convex + ModeloPrecios + CajaInventario | BE92: Calidad difiere: legacy=Comercial Superior vs modeloPrecios=Rareza
A93: 92 | B93: 08-dic-2025 | C93: Corazón de la noche | D93: 1.31 | E93: Verde Limón | F93: COMERCIAL FINA | G93: 1 | H93: Corazón | I93: Largo x Ancho | J93: 6.5 × 8.0 × 4.5 mm | K93: Gema | L93: 676746 | O93: ASESOR | P93: Juan Manuel Escobar Ramirez | Q93: VENDIDA | R93: https://tierramadre.app/p/92 | S93: Secretos del Bosque | T93: Esmereogenesis | AR93: =IFERROR(VLOOKUP($X93,Lotes!$A:$E,5,FALSE())*$U93,"") | AS93: =IF($L93="","",$L93*2.6) -> 1759539.6 | AU93: 1355000 | AV93: 1355000 | AW93: 1355000 | AX93: Juan Manuel Escobar Ramirez | AY93: CARTERA | BA93: https://tierramadre.app/product/92 | BB93: https://drive.google.com/drive/folders/1yF1MwteXvTmdoqRQp170D6UFdMKxCV-h | BC93: 2026-07-15-corazon-de-la-noche-item-92 | BD93: Legacy + Fotosintesis/Convex + CajaInventario
A94: 93 | B94: 08-dic-2025 | C94: Julieta | D94: 1.74 | E94: Verde Limón | F94: COMERCIAL FINA | G94: 1 | H94: Ovalo | I94: Largo x Ancho | J94: 7.4 × 5.5 mm | K94: Gema | L94: 897000 | O94: OFI.CALI | Q94: DISPONIBLE | R94: https://tierramadre.app/p/93 | S94: Secretos del Bosque | X94: C-045 | AF94: Gema Facetada | AR94: =IFERROR(VLOOKUP($X94,Lotes!$A:$E,5,FALSE())*$U94,"") -> 0 | AS94: =IF($L94="","",$L94*2.6) -> 2332200 | AU94: 1973717 | AV94: 1973717 | AW94: 1973717 | AX94: Tierra Madre | AY94: Disponible | BA94: https://tierramadre.app/product/93 | BB94: https://drive.google.com/drive/folders/13q8tV1Udx1FsCg6Ylx7gCZt4fm7iqvIe | BC94: 2026-07-15-modelo-item-93-dos-luciernagas | BD94: Legacy + Fotosintesis/Convex + ModeloPrecios + CajaInventario | BE94: Calidad difiere: legacy=COMERCIAL FINA vs modeloPrecios=C. Fina
A95: 94 | B95: 08-dic-2025 | C95: L:A-26B Esencia del Bosque | D95: 1.31 | E95: Verde Natural | F95: COMERCIAL SUPERIOR | G95: 1 | H95: Cuadrada | I95: Largo x Ancho | J95: 7.5 × 6.6 × 3.7 mm | K95: Gema | L95: 950000 | O95: OFI.CALI | P95: M.Campuzano | Q95: ESMEREOGENESIS | R95: https://tierramadre.app/p/94 | S95: Fénix | T95: Esmereogenesis | AR95: =IFERROR(VLOOKUP($X95,Lotes!$A:$E,5,FALSE())*$U95,"") | AS95: =IF($L95="","",$L95*2.6) -> 2470000 | AU95: 1900000 | AV95: 1425000 | AW95: 1125000 | AX95: M.Campuzano | AY95: CARTERA Claudia Altamirano | BA95: https://tierramadre.app/product/94 | BB95: https://drive.google.com/drive/folders/1BuX9AhCd11lZ-BqroqZa0kHxkwZWjP87 | BC95: 2026-07-18-l-a-26b-esencia-del-bosque-item-94 | BD95: Legacy + Fotosintesis/Convex + CajaInventario
A96: 95 | B96: 08-dic-2025 | C96: Magia Estelar | D96: 0.22 | E96: Verde Limón | F96: COMERCIAL FINA | G96: 1 | H96: Redonda | I96: Diámetro | J96: 38 mm | K96: Gema | L96: 113652 | O96: ASESOR | P96: M.Echeverry | Q96: VENDIDA | R96: https://tierramadre.app/p/95 | S96: Secretos del Bosque | AR96: =IFERROR(VLOOKUP($X96,Lotes!$A:$E,5,FALSE())*$U96,"") | AS96: =IF($L96="","",$L96*2.6) -> 295495.2 | AU96: 272765 | AV96: 272765 | AW96: 0 | AX96: M.Echeverry | AY96: VENDIDO | BA96: https://tierramadre.app/product/95 | BB96: https://drive.google.com/drive/folders/1ODNpsemdS7DqQ42P3REFcItJCTxBNfGf | BC96: 2026-07-18-magia-estelar-item-95 | BD96: Legacy + Fotosintesis/Convex + CajaInventario
A97: 96 | B97: 08-dic-2025 | C97: Caja de Pandora | D97: 0.33 | E97: Verde Azul | F97: COMERCIAL SÚPER FINA | G97: 1 | H97: Cuadrada | I97: Largo x Ancho | J97: 40 mm | K97: Gema | L97: 297297 | O97: ASESOR | P97: Paola Daza | Q97: VENDIDA | R97: https://tierramadre.app/p/96 | S97: Secretos del Bosque | T97: Legalizada | AR97: =IFERROR(VLOOKUP($X97,Lotes!$A:$E,5,FALSE())*$U97,"") | AS97: =IF($L97="","",$L97*2.6) -> 772972.2 | AU97: 773000 | AV97: 749810 | AW97: 0 | AX97: Paola Daza | AY97: VENDIDO | BA97: https://tierramadre.app/product/96 | BB97: https://drive.google.com/drive/folders/1D3MaOpwHfh1MSnlQbVi0QxFMWm1SQEKb | BC97: 2026-07-18-caja-de-pandora-item-96 | BD97: Legacy + Fotosintesis/Convex + CajaInventario
A98: 97 | B98: 08-dic-2025 | C98: Almas Gemelas | D98: 0.86 | E98: Verde Limón | F98: COMERCIAL FINA | G98: 2 | H98: Cuadrada | I98: Largo x Ancho | J98: 4.6 × 4.4 mm | K98: Gema | L98: 200000 | O98: OFI.CALI | P98: M.Campuzano | Q98: DISPONIBLE | R98: https://tierramadre.app/p/97 | S98: Secretos del Bosque | X98: C-046 | AF98: Gema Facetada | AQ98: 0.64 | AR98: =IFERROR(VLOOKUP($X98,Lotes!$A:$E,5,FALSE())*$U98,"") -> 0 | AS98: =IF($L98="","",$L98*2.6) -> 520000 | AU98: 1551956 | AV98: 1551956 | AW98: 1551956 | AX98: Tierra Madre | AY98: Disponible | BA98: https://tierramadre.app/product/97 | BB98: https://drive.google.com/drive/folders/1vX5FaSfLZzSvij5gEmuZXoywtV8H9QFx | BC98: 2026-07-13-almas-gemelas-item-97 | BD98: Legacy + Fotosintesis/Convex + ModeloPrecios + CajaInventario | BE98: Calidad difiere: legacy=COMERCIAL FINA vs modeloPrecios=C. Fina | Caja (snapshot) registra comprador 'Tierra Madre' vs asesor actual 'M.Campuzano' — revisar si son ventas distintas o la copia está desactualizada.
A99: 98 | B99: 08-dic-2025 | C99: Campanita | D99: 0.18 | E99: Verde Vívido | F99: FINA ESENCIAL | G99: 1 | H99: Cuadrada | I99: Largo x Ancho | J99: 2.7 × 3.8 × 2.3 mm | K99: Gema | L99: 163000 | O99: ASESOR | P99: Juan Manuel Escobar Ramirez | R99: https://tierramadre.app/p/98 | S99: Secretos del Bosque | AR99: =IFERROR(VLOOKUP($X99,Lotes!$A:$E,5,FALSE())*$U99,"") | AS99: =IF($L99="","",$L99*2.6) -> 423800 | AU99: 489000 | AV99: 489000 | AW99: 489000 | AX99: Juan Manuel Escobar Ramirez | AY99: PRODUCCION | BA99: https://tierramadre.app/product/98 | BB99: https://drive.google.com/drive/folders/17rwcGQ4txDDMm8GzR9taH2bBHWHymm2k | BC99: 2026-07-18-campanita-item-98 | BD99: Legacy + Fotosintesis/Convex + CajaInventario
A100: 99 | B100: 08-dic-2025 | C100: Reflejo Divino | D100: 0.44 | E100: Verde Vívido | F100: COMERCIAL SÚPER FINA | G100: 1 | H100: Esmeralda | I100: Largo x Ancho | J100: 5.6 × 3.6 × 2.9 mm | K100: Gema | L100: 396000 | O100: ASESOR | P100: Alvaro Pelaez | Q100: VENDIDA | R100: https://tierramadre.app/p/99 | S100: Secretos del Bosque | T100: Legalizada | AR100: =IFERROR(VLOOKUP($X100,Lotes!$A:$E,5,FALSE())*$U100,"") | AS100: =IF($L100="","",$L100*2.6) -> 1029600 | AU100: 990000 | AV100: 800811 | AW100: 37 | AX100: Alvaro Pelaez | AY100: VENDIDO | BA100: https://tierramadre.app/product/99 | BB100: https://drive.google.com/drive/folders/1FFxB62Ue-8qyD_nfpKmFFeBdTqtBp8NV | BC100: 2026-07-18-reflejo-divino-item-99 | BD100: Legacy + Fotosintesis/Convex + Ventas + CajaInventario
...

Sheet Lotes
A1: loteId | B1: providerNombre | C1: fechaRecepcion | D1: pesoTotalQuilates | E1: costoTotalCOP | F1: unidadesDeclaradas | G1: formaPago | H1: metodoContado | I1: fechaVencimiento | J1: numeroCuotas | K1: numeroFactura | L1: urlFactura | M1: notas | N1: estado | O1: renombreLote | P1: tratamiento | Q1: mina | R1: sede | S1: operadorNombre | T1: operadorRol | U1: mostrarComoLote
A2: B-001·anulado | B2: Edwin Mauricio Ruiz | C2: 2026-05-26 00:00:00 | E2: 150000 | F2: 1 | G2: contado | H2: transferencia | N2: cancelado | R2: B | S2: Kevin Pineda Pérez | T2: captura
A3: C-001 | B3: Edwin Mauricio Ruiz | C3: 2026-05-25 00:00:00 | D3: 37.3 | E3: 4900000 | F3: 190 | G3: contado | H3: transferencia | M3: Perfecto para topitos ,buen tono , buen brillo , 7,3ct calibrados | N3: abierto
A4: C-002 | B4: Edwin Mauricio Ruiz | C4: 2026-05-25 00:00:00 | D4: 9.63 | E4: 1200000 | F4: 2 | G4: credito | H4: transferencia | I4: 2026-08-31 00:00:00 | J4: 1 | K4: N/A | L4: N/A | M4: Exoticas | N4: publicado
A5: C-003 | B5: Edwin Mauricio Ruiz | C5: 2026-05-25 00:00:00 | D5: 71 | E5: 650000 | F5: 5 | G5: contado | H5: transferencia | M5: Comprado 15 mayo del 2026 Morralla de calidad Difícil de conseguir | Reabierto por kpp.coomunity@gmail.com | N5: publicado | O5: Rocas de Venus | P5: Estándar | Q5: Boyacá | R5: C | S5: Maritza Rodriguez | T5: captura
A6: C-004 | B6: Edwin Mauricio Ruiz | C6: 2026-05-25 00:00:00 | D6: 331.1 | E6: 500000 | F6: 7 | G6: contado | H6: transferencia | M6: La mitad del lote (6)/ea para producto propio | N6: publicado | O6: Asteroides Verdes II | P6: Natural | Q6: Boyacá | R6: C | S6: Maritza Rodriguez | T6: captura
A7: C-005 | B7: Edwin Mauricio Ruiz | C7: 2026-05-25 00:00:00 | D7: 300 | E7: 500000 | F7: 2 | G7: contado | H7: transferencia | N7: publicado | O7: Asteroides Verdes III | P7: Natural | Q7: Boyacá | R7: C | S7: Maritza Rodriguez | T7: captura
A8: C-006 | B8: Edwin Mauricio Ruiz | C8: 2026-05-25 00:00:00 | E8: 1300000 | F8: 6 | G8: contado | H8: transferencia | M8: Reserva Talismanes de Brielah | Reabierto por kpp.coomunity@gmail.com | N8: abierto | O8: Jardín Secreto | P8: Estándar | Q8: Boyacá | R8: C | S8: Maritza Rodriguez | T8: captura
A9: C-007 | B9: Edwin Mauricio Ruiz | C9: 2026-05-25 00:00:00 | D9: 40.4 | E9: 1010000 | F9: 6 | G9: contado | H9: transferencia | M9: . | Reabierto por seguimientoproduccion1@gmail.com | N9: publicado | O9: Infinita Felicidad | P9: Pulida | Q9: Boyacá | R9: C | S9: Maritza Rodriguez | T9: captura
A10: C-008 | B10: Edwin Mauricio Ruiz | C10: 2026-05-26 00:00:00 | E10: 5250000 | F10: 4 | G10: contado | H10: transferencia | M10: Para Mercado Internacional | N10: publicado | O10: Trascendencia | P10: Estándar | Q10: Chivor | R10: C | S10: Maritza Rodriguez | T10: captura
A11: C-009 | B11: Edwin Mauricio Ruiz | C11: 2026-05-26 00:00:00 | D11: 1.43 | E11: 3400000 | F11: 1 | G11: credito | I11: 2026-07-30 00:00:00 | J11: 1 | N11: publicado | O11: Orbita Lunar | P11: Estándar | Q11: Muzo | R11: C | S11: Maritza Rodriguez | T11: captura
A12: C-010 | B12: Edwin Mauricio Ruiz | C12: 2026-05-26 00:00:00 | E12: 2010000 | F12: 6 | G12: credito | I12: 2026-06-20 00:00:00 | J12: 1 | M12: Fiadas y con descuento 25% | Reabierto por kvn3toj@gmail.com: Re-dividir C-010: separar 10 gemas nombradas de #351 (Andromeda, Pandora, Namek, Cinturon de Orion) | N12: publicado | O12: Lluvia de Estrellas - L | P12: Estándar | Q12: Chivor | R12: C | S12: Maritza Rodriguez | T12: captura
A13: C-011 | B13: Edwin Mauricio Ruiz | C13: 2026-05-26 00:00:00 | D13: 5.17 | E13: 3100000 | F13: 3 | G13: contado | H13: transferencia | M13: Escazas - Difícil de Conseguir | N13: publicado | O13: Otoño | P13: Estándar | Q13: Boyacá | R13: C | S13: Maritza Rodriguez | T13: captura
A14: C-012 | B14: Edwin Mauricio Ruiz | C14: 2026-05-26 00:00:00 | D14: 37.3 | E14: 4900000 | F14: 8 | G14: contado | H14: transferencia | N14: publicado | O14: Lluvia de Bendiciones | P14: Estándar | Q14: Boyacá | R14: C | S14: Maritza Rodriguez | T14: captura
A15: C-013 | B15: Edwin Mauricio Ruiz | C15: 2026-05-26 00:00:00 | D15: 79 | E15: 500000 | F15: 1 | G15: contado | H15: transferencia | N15: publicado | O15: Rocas Sagradas - G2 | P15: Estándar | Q15: Boyacá | R15: C | S15: Maritza Rodriguez | T15: captura
A16: C-014 | B16: Edwin Mauricio Ruiz | C16: 2026-05-26 00:00:00 | E16: 575000 | F16: 1 | G16: contado | H16: transferencia | M16: montura para topitos | N16: publicado | O16: Montura Topitos Plata Rodinada | P16: Rodinado | R16: C | S16: Maritza Rodriguez | T16: captura
A17: C-015 | B17: Edwin Mauricio Ruiz | C17: 2026-05-26 00:00:00 | D17: 0.86 | E17: 900000 | F17: 9 | G17: credito | I17: 2026-08-31 00:00:00 | J17: 1 | M17: Reabierto por seguimientoproduccion1@gmail.com | N17: cerrado | O17: Libélulas de la Sabana II | P17: Estándar | Q17: Boyacá | R17: C | S17: Maritza Rodriguez | T17: captura
A18: C-016 | B18: Edwin Mauricio Ruiz | C18: 2026-05-26 00:00:00 | E18: 450000 | F18: 1 | G18: credito | I18: 2026-07-31 00:00:00 | J18: 11 | M18: Diseño Especial | N18: publicado | O18: Belleza del Caribe | P18: Natural | Q18: Boyacá | R18: C | S18: Maritza Rodriguez | T18: captura
A19: C-017 | B19: Edwin Mauricio Ruiz | C19: 2026-05-26 00:00:00 | D19: 47.47 | E19: 378000000 | F19: 18 | G19: contado | H19: transferencia | M19: Lote Origen que se movio por todo el mundo | N19: abierto | O19: Origen | P19: Variado | Q19: Chivor | R19: C | S19: Maritza Rodriguez | T19: captura
A20: C-018 | B20: Edwin Mauricio Ruiz | C20: 2026-06-17 00:00:00 | D20: 1.43 | E20: 2717000 | F20: 12 | G20: credito | I20: 2026-07-31 00:00:00 | J20: 1 | M20: Chispitas , estan calibradas para desarrollar productos propios .se abono 1.700.000 contado .saldo Julio 1.017.000 | N20: publicado | O20: Moléculas de Luz | P20: Perma | Q20: Muzo | R20: C | S20: Maritza Rodriguez | T20: captura
A21: C-019 | B21: Edwin Mauricio Ruiz | C21: 2026-06-17 00:00:00 | D21: 0.49 | E21: 600000 | F21: 3 | G21: contado | H21: transferencia | N21: publicado | O21: Partículas de Luz | P21: Perma | Q21: Muzo | R21: C | S21: Maritza Rodriguez | T21: captura
A22: C-020 | B22: Edwin Mauricio Ruiz | C22: 2026-06-17 00:00:00 | D22: 0.22 | E22: 550000 | F22: 1 | G22: contado | H22: transferencia | M22: Reabierto por kpp.coomunity@gmail.com | N22: publicado | O22: Quinto Elemento | P22: Perma | Q22: Muzo | R22: C | S22: Maritza Rodriguez | T22: captura
A23: C-021 | B23: Edwin Mauricio Ruiz | C23: 2026-06-18 00:00:00 | D23: 0.8 | E23: 120000 | F23: 1 | G23: contado | H23: transferencia | M23: Anillo se compro a un proveedor mayorista diferente | N23: publicado | O23: Jupiter | P23: Robinada | Q23: Boyacá | R23: C | S23: Maritza Rodriguez | T23: captura
A24: C-022 | B24: Edwin Mauricio Ruiz | C24: 2026-06-18 00:00:00 | D24: 0.8 | E24: 71400 | F24: 1 | G24: contado | H24: transferencia | M24: Reabierto por kpp.coomunity@gmail.com | N24: publicado | O24: Kiwi | P24: Robinada | Q24: Boyacá | R24: C | S24: Maritza Rodriguez | T24: captura
A25: C-023 | B25: Taller de Bronce El Rey, Joyas Artesanales | C25: 2026-07-08 00:00:00 | E25: 512600 | F25: 3 | G25: contado | H25: transferencia | M25: Línea de producción: Joyería Artesanal · Tipo de esmeralda: Gota y Piedra Cristal | Reabierto por kpp.coomunity@gmail.com | Reabierto por kpp.coomunity@gmail.com | N25: publicado | O25: Renacer de Primavera | R25: C | S25: Kevin Pineda Pérez | T25: captura
A26: C-024 | B26: Taller de Bronce El Rey, Joyas Artesanales | C26: 2026-07-08 00:00:00 | E26: 540000 | F26: 2 | G26: contado | H26: transferencia | N26: publicado | O26: Susurro de Otoño | R26: C | S26: Kevin Pineda Pérez | T26: captura
A27: C-025 | B27: Taller de Bronce El Rey, Joyas Artesanales | C27: 2026-07-08 00:00:00 | E27: 324000 | F27: 2 | G27: contado | H27: transferencia | N27: publicado | O27: Máximo Esplendor | R27: C | S27: Kevin Pineda Pérez | T27: captura
A28: C-026 | B28: Taller de Bronce El Rey, Joyas Artesanales | C28: 2026-07-08 00:00:00 | E28: 70000 | F28: 1 | G28: contado | H28: transferencia | N28: publicado | O28: Infinito Esmeralda | R28: C | S28: Kevin Pineda Pérez | T28: captura
A29: C-027 | B29: Taller de Bronce El Rey, Joyas Artesanales | C29: 2026-07-08 00:00:00 | E29: 270000 | F29: 4 | G29: contado | H29: transferencia | N29: publicado | O29: Pecado orginal | R29: C | S29: Kevin Pineda Pérez | T29: captura
A30: C-028 | B30: Taller de Bronce El Rey, Joyas Artesanales | C30: 2026-07-08 00:00:00 | E30: 340000 | F30: 3 | G30: contado | H30: transferencia | N30: publicado | O30: Naturaleza viva | R30: C | S30: Kevin Pineda Pérez | T30: captura
A31: C-029 | B31: Taller de Bronce El Rey, Joyas Artesanales | C31: 2026-07-08 00:00:00 | E31: 130000 | F31: 2 | G31: contado | H31: transferencia | N31: publicado | O31: kundalini | R31: C | S31: Kevin Pineda Pérez | T31: captura
A32: C-030 | B32: Taller de Bronce El Rey, Joyas Artesanales | C32: 2026-07-08 00:00:00 | E32: 243000 | F32: 3 | G32: contado | H32: transferencia | N32: publicado | O32: Lirios del Agua | R32: C | S32: Kevin Pineda Pérez | T32: captura
A33: C-031 | B33: Taller de Bronce El Rey, Joyas Artesanales | C33: 2026-07-08 00:00:00 | E33: 110000 | F33: 2 | G33: contado | H33: transferencia | N33: publicado | O33: Maestros del aire | R33: C | S33: Kevin Pineda Pérez | T33: captura
A34: C-032 | B34: Taller de Bronce El Rey, Joyas Artesanales | C34: 2026-07-08 00:00:00 | E34: 150000 | F34: 1 | G34: contado | H34: transferencia | N34: publicado | O34: Soberana | R34: C | S34: Kevin Pineda Pérez | T34: captura
A35: C-033 | B35: Taller de Bronce El Rey, Joyas Artesanales | C35: 2026-07-08 00:00:00 | E35: 1230000 | F35: 1 | G35: contado | H35: transferencia | N35: publicado | O35: Noche Eclipsada | R35: C | S35: Kevin Pineda Pérez | T35: captura
A36: C-034 | B36: Edwin Mauricio Ruiz | C36: 2026-07-10 00:00:00 | D36: 142.48 | E36: 585000 | F36: 5 | G36: contado | H36: transferencia | M36: Migración seedBucketC: valores de sub-lote suman $584.950 vs $585.000 declarado (gap $50, rounding en la fuente) — ver reporte. | N36: publicado | O36: Rocas Lunares | R36: C
A37: C-035 | B37: Taller de Bronce El Rey, Joyas Artesanales | C37: 2026-07-10 00:00:00 | E37: 261000 | F37: 1 | G37: contado | H37: transferencia | M37: Migración seedBucketC: lote base en plata, sin ítems individuales aún. | N37: cerrado | O37: Lote base 9 anillos de mujer | R37: C
A38: C-036 | B38: Joyería Legado | C38: 2026-07-10 00:00:00 | E38: 255000 | F38: 1 | G38: contado | H38: transferencia | M38: seedInsumosMarketing: 3 cuentas esféricas verdes ($85.000 c/u). Antes "Balines". Proveedor asumido: Joyería Legado (confirmar). | N38: cerrado | O38: Esferas del Dragón (cuentas verdes) | R38: C
A39: C-037 | B39: Joyería Legado | C39: 2026-07-10 00:00:00 | E39: 24000 | F39: 1 | G39: contado | H39: transferencia | M39: seedInsumosMarketing: 6 cadenas ($4.000 c/u). Proveedor asumido: Joyería Legado (confirmar). | N39: cerrado | O39: Cadenas de baño en oro | R39: C
A40: C-038 | B40: Joyería Legado | C40: 2026-07-10 00:00:00 | E40: 278100 | F40: 1 | G40: contado | H40: transferencia | M40: seedInsumosMarketing: 14 pares: 4mm×6, 3mm×6, 5mm×1, 2mm×1. 1 suelto 3mm usado en Perlita #260. Proveedor asumido: Joyería Legado (confirmar). | N40: cerrado | O40: Topos Redondos (postes aretes) | R40: C
A41: C-039 | B41: Joyería Legado | C41: 2026-07-10 00:00:00 | E41: 291500 | F41: 1 | G41: contado | H41: transferencia | M41: seedInsumosMarketing: 15 pares: 5mm×1, 4x4.5mm×7, 3.2mm×6, 2mm×1. 1 suelto 3.2mm usado en Luz del Firmamento #257. Proveedor asumido: Joyería Legado (confirmar). | N41: cerrado | O41: Topos Planos (postes aretes) | R41: C
A42: C-040 | B42: Joyería Legado | C42: 2026-07-10 00:00:00 | E42: 500000 | F42: 1 | G42: contado | H42: transferencia | M42: seedInsumosMarketing: 20 pares ($25.000 c/u). 3 usados (Almas Gemelas #97, Dos Pequitas #77, Reflejos del Sol). Stock 17. Proveedor asumido: Joyería Legado (confirmar). | N42: cerrado | O42: Pares Topos #3 (postes plata) | R42: C
A43: C-041 | B43: Joyería Legado | C43: 2026-07-10 00:00:00 | E43: 500000 | F43: 1 | G43: contado | H43: transferencia | M43: seedInsumosMarketing: 14 pares 4.3mm ($35.714 c/u). 3 usados (Ojos del Universo #76, Hadas del Bosque #89, Destellos Gemelos). Stock 11. Proveedor asumido: Joyería Legado (confirmar). | N43: cerrado | O43: Pares Topos #4 (postes plata 4.3mm) | R43: C
A44: C-042 | B44: Edwin Mauricio Ruiz | C44: 2026-07-11 00:00:00 | D44: 1.48 | E44: 735000 | F44: 2 | G44: contado | H44: transferencia | M44: División de #363 'Igualdad' (C-012, 4 gemas facetadas rectangulares) en 2 pares. C-012 no reabrible (#359 VENDIDA), por eso lote dedicado. Precio mitad/mitad por par. Sub-lotes: Guardianas Gemelas + Mellizas del Alba. | Reabierto: Rework: colapsar pares en 1 ítem c/u (un QR por par) | N44: publicado | O44: Igualdad — Guardianas y Mellizas | R44: C
A45: C-043 | F45: 1 | M45: Recuperado: referenciado por 1 ítem(s), faltaba en catálogo Lotes — verificar proveedor/costo | N45: abierto | O45: Infinito Amor
A46: C-044 | F46: 1 | M46: Recuperado: referenciado por 1 ítem(s), faltaba en catálogo Lotes — verificar proveedor/costo | N46: abierto | O46: Misterio Profundo
A47: C-045 | F47: 1 | M47: Recuperado: referenciado por 1 ítem(s), faltaba en catálogo Lotes — verificar proveedor/costo | N47: abierto | O47: Dos Luciérnagas
A48: C-046 | F48: 21 | M48: Recuperado: referenciado por 21 ítem(s), faltaba en catálogo Lotes — verificar proveedor/costo | N48: abierto | O48: Hadas del Bosque + Chatones Planos
A49: C-047 | F49: 2 | M49: Recuperado: referenciado por 2 ítem(s), faltaba en catálogo Lotes — verificar proveedor/costo | N49: abierto | O49: Luz del Firmamento (Topo Plano 3,2mm)
A50: C-048 | F50: 1 | M50: Recuperado: referenciado por 1 ítem(s), faltaba en catálogo Lotes — verificar proveedor/costo | N50: abierto | O50: Mariposas de la Montaña
A51: C-049 | B51: Joyería Legado | C51: 2026-07-15 | E51: 87400 | F51: 1 | M51: Recuperado: referenciado por 1 ítem(s), faltaba en catálogo Lotes — verificar proveedor/costo | N51: abierto | O51: Topito Plano Solitario 5mm
A52: C-050 | F52: 1 | M52: Recuperado: referenciado por 1 ítem(s), faltaba en catálogo Lotes — verificar proveedor/costo | N52: abierto | O52: Ojos del Universo (chatones mariposa)
A53: C-051 | F53: 1 | M53: Recuperado: referenciado por 1 ítem(s), faltaba en catálogo Lotes — verificar proveedor/costo | N53: abierto | O53: Dos Pequitas
A54: C-052 | F54: 1 | M54: Recuperado: referenciado por 1 ítem(s), faltaba en catálogo Lotes — verificar proveedor/costo | N54: abierto | O54: Poseidón (falta gema)
A55: C-053 | F55: 7 | M55: Recuperado: referenciado por 7 ítem(s), faltaba en catálogo Lotes — verificar proveedor/costo | N55: abierto | O55: Grecia
A56: C-054 | B56: Joyería Legado | C56: 2026-07-15 | E56: 1279000 | F56: 1 | M56: Recuperado: referenciado por 1 ítem(s), faltaba en catálogo Lotes — verificar proveedor/costo | N56: abierto | O56: Anillos Joyero Cali 4 de plata y 1 de oro
A57: C-055 | F57: 1 | M57: Recuperado: referenciado por 1 ítem(s), faltaba en catálogo Lotes — verificar proveedor/costo | N57: abierto | O57: El Secreto de Tena
A58: C-057 | F58: 2 | M58: Recuperado: referenciado por 2 ítem(s), faltaba en catálogo Lotes — verificar proveedor/costo | N58: abierto | O58: Ojo de la Pantera
A59: C-058 | F59: 1 | M59: Recuperado: referenciado por 1 ítem(s), faltaba en catálogo Lotes — verificar proveedor/costo | N59: abierto | O59: Jazmín
A60: C-059 | F60: 1 | M60: Recuperado: referenciado por 1 ítem(s), faltaba en catálogo Lotes — verificar proveedor/costo | N60: abierto | O60: Libélulas de la Sabana
A61: C-060 | F61: 1 | M61: Recuperado: referenciado por 1 ítem(s), faltaba en catálogo Lotes — verificar proveedor/costo | N61: abierto | O61: Viento Nocturno
A62: C-061 | B62: Joyería Legado | C62: 2026-07-15 | E62: 500000 | F62: 1 | M62: Recuperado: referenciado por 1 ítem(s), faltaba en catálogo Lotes — verificar proveedor/costo | N62: abierto | O62: Asteroides Verdes III
A63: C-062 | F63: 1 | M63: Recuperado: referenciado por 1 ítem(s), faltaba en catálogo Lotes — verificar proveedor/costo | N63: abierto | O63: Frozen
A64: C-063 | F64: 2 | M64: Recuperado: referenciado por 2 ítem(s), faltaba en catálogo Lotes — verificar proveedor/costo | N64: abierto | O64: Manillas Colombia
A65: C-065 | B65: Joyería Legado | C65: 2026-07-15 | E65: 1450050 | F65: 14 | M65: Recuperado: referenciado por 14 ítem(s), faltaba en catálogo Lotes — verificar proveedor/costo | N65: abierto | O65: Chatones de Mariposa 4,2mm
A66: C-067 | F66: 12 | M66: Recuperado: referenciado por 12 ítem(s), faltaba en catálogo Lotes — verificar proveedor/costo | N66: abierto | O66: Innombradas
A67: C-068 | F67: 10 | M67: Recuperado: referenciado por 10 ítem(s), faltaba en catálogo Lotes — verificar proveedor/costo | N67: abierto | O67: Elementales
A68: C-069 | B68: Joyería Legado | C68: 2026-07-15 | F68: 3 | M68: Recuperado: referenciado por 3 ítem(s), faltaba en catálogo Lotes — verificar proveedor/costo | N68: abierto | O68: Destino
A69: C-070 | F69: 13 | M69: Recuperado: referenciado por 13 ítem(s), faltaba en catálogo Lotes — verificar proveedor/costo | N69: abierto | O69: Intuición
A70: C-071 | F70: 1 | M70: Recuperado: referenciado por 1 ítem(s), faltaba en catálogo Lotes — verificar proveedor/costo | N70: abierto | O70: Ojitos del Mar
A71: C-072 | F71: 1 | M71: Recuperado: referenciado por 1 ítem(s), faltaba en catálogo Lotes — verificar proveedor/costo | N71: abierto | O71: Pegasus
A72: C-073 | F72: 1 | M72: Recuperado: referenciado por 1 ítem(s), faltaba en catálogo Lotes — verificar proveedor/costo | N72: abierto | O72: Luna Creciente
A73: C-074 | F73: 1 | M73: Recuperado: referenciado por 1 ítem(s), faltaba en catálogo Lotes — verificar proveedor/costo | N73: abierto | O73: Gota del Amazonas
A74: C-075 | F74: 2 | M74: Recuperado: referenciado por 2 ítem(s), faltaba en catálogo Lotes — verificar proveedor/costo | N74: abierto | O74: Gotita de Amor
A75: C-076 | B75: Joyería Legado | C75: 2026-07-15 | F75: 2 | M75: Recuperado: referenciado por 2 ítem(s), faltaba en catálogo Lotes — verificar proveedor/costo | N75: abierto
A76: MED-001 | B76: Edwin Mauricio Ruiz | C76: 2026-07-14 00:00:00 | E76: 22400 | F76: 1 | G76: contado | H76: efectivo | N76: abierto | R76: MED
A77: MED-002 | B77: Edwin Mauricio Ruiz | C77: 2026-07-14 00:00:00 | E77: 1 | F77: 1 | G77: contado | H77: efectivo | N77: abierto | R77: MED
A78: MED-003 | B78: Edwin Mauricio Ruiz | C78: 2026-07-14 00:00:00 | E78: 1 | F78: 1 | G78: contado | H78: efectivo | N78: abierto | R78: MED
A79: MED-004 | B79: Edwin Mauricio Ruiz | C79: 2026-07-13 00:00:00 | E79: 790162 | F79: 1 | G79: contado | H79: efectivo | N79: abierto | R79: MED
A80: MED-005 | B80: Edwin Mauricio Ruiz | C80: 2026-07-13 00:00:00 | E80: 491240 | F80: 1 | G80: contado | H80: efectivo | N80: abierto | R80: MED
A81: MED-006 | B81: Edwin Mauricio Ruiz | C81: 2026-07-13 00:00:00 | E81: 629919 | F81: 1 | G81: contado | H81: efectivo | N81: abierto | R81: MED
A82: MED-007 | B82: Edwin Mauricio Ruiz | C82: 2026-07-13 00:00:00 | E82: 618838 | F82: 1 | G82: contado | H82: efectivo | N82: abierto | R82: MED
A83: MED-008 | B83: Edwin Mauricio Ruiz | C83: 2026-07-14 00:00:00 | E83: 1 | F83: 1 | G83: contado | H83: efectivo | N83: abierto | R83: MED
A84: MED-009 | B84: Edwin Mauricio Ruiz | C84: 2026-07-14 00:00:00 | E84: 1 | F84: 1 | G84: contado | H84: efectivo | N84: abierto | R84: MED
A85: MED-010 | B85: Edwin Mauricio Ruiz | C85: 2026-07-14 00:00:00 | E85: 1 | F85: 1 | G85: contado | H85: efectivo | N85: abierto | R85: MED
A86: MED-011 | B86: Edwin Mauricio Ruiz | C86: 2026-07-14 00:00:00 | E86: 1 | F86: 1 | G86: contado | H86: efectivo | N86: abierto | R86: MED
A87: MED-012 | B87: Edwin Mauricio Ruiz | C87: 2026-07-13 00:00:00 | E87: 2071050 | F87: 8 | G87: contado | H87: efectivo | N87: abierto | R87: MED
... A98: MED-024 | B98: Edwin Mauricio Ruiz | C98: 2026-07-13 00:00:00 | E98: 1 | F98: 1 | G98: contado | H98: efectivo | N98: abierto | R98: MED
A99: S-001 | B99: Edwin Mauricio Ruiz | C99: 2026-05-26 00:00:00 | D99: 47.47 | E99: 378000000 | F99: 18 | G99: contado | H99: transferencia | M99: lote Origen que recorrio el mundo | N99: abierto | O99: Origen | P99: Variado | Q99: Chivor y Muzo | R99: S | S99: Maritza Rodriguez | T99: captura

Sheet Sublotes
A1: subLoteId | B1: parentLoteId | C1: sede | D1: nombre | E1: itemIds | F1: unidades | G1: totalCostoCOP | H1: estado | I1: mostrarComoLote | J1: notas | K1: createdAt
A2: C-024-G1 | B2: C-024 | C2: C | D2: Susurro de Otoño | E2: 398, 399 | F2: 2 | G2: 540000 | H2: activa | K2: 2026-07-08T09:40:59.890Z
A3: C-025-G1 | B3: C-025 | C3: C | D3: Máximo Esplendor | E3: 400, 401 | F3: 2 | G3: 324000 | H3: activa | K3: 2026-07-08T09:41:36.289Z
A4: C-027-G1 | B4: C-027 | C4: C | D4: Pecado orginal | E4: 403, 404, 405, 406 | F4: 4 | G4: 269997 | H4: activa | K4: 2026-07-08T10:54:56.925Z
A5: C-028-G1 | B5: C-028 | C5: C | D5: Naturaleza viva | E5: 407, 408, 409 | F5: 3 | G5: 339999 | H5: activa | K5: 2026-07-08T11:04:10.532Z
A6: C-029-G1 | B6: C-029 | C6: C | D6: kundalini | E6: 410, 411 | F6: 2 | G6: 130000 | H6: activa | K6: 2026-07-08T11:09:30.547Z
A7: C-030-G1 | B7: C-030 | C7: C | D7: Lirios del Agua | E7: 412, 413, 414 | F7: 3 | G7: 243001 | H7: activa | K7: 2026-07-08T11:14:28.335Z
A8: C-031-G1 | B8: C-031 | C8: C | D8: Maestros del aire | E8: 415, 416 | F8: 2 | G8: 110000 | H8: activa | K8: 2026-07-08T11:18:51.513Z
A9: C-042-G1 | B9: C-042 | C9: C | D9: Guardianas Gemelas | E9: 467, 468 | F9: 2 | G9: 367500 | H9: archivada | J9: Par para dijes. Ex 'Igualdad Dijes' (#363). | K9: 2026-07-12T01:02:42.515Z
A10: C-042-G2 | B10: C-042 | C10: C | D10: Mellizas del Alba | E10: 469, 470 | F10: 2 | G10: 367500 | H10: archivada | J10: Par para topitos. Ex 'Igualdad Topitos' (#363). | K10: 2026-07-12T01:02:44.192Z

Sheet Proveedores
A1: nombreORazonSocial | B1: nit | C1: cedula | D1: direccion | E1: telefono | F1: email | G1: tipo | H1: notas
A2: Edwin Mauricio Ruiz | C2: 80179071 | D2: carrera6#14-74 Edificio Explinter Oficina 904 | E2: 57 3100000 | F2: gerenciatel@gmail.com | G2: gemas | H2: Proveedor Exclusivo de gemas aliado estrategico
A3: Joyería Artesanal | G3: joyas
A4: Taller de Bronce El Rey, Joyas Artesanales | G4: joyas
A5: Joyería Legado | D5: Bogotá (contacto: Giovanny Ríos) | E5: 3118660925 | G5: insumos

Sheet Clientes
A1: nombre | B1: nit | C1: cedula | D1: direccion | E1: telefono | F1: email | G1: tipo | H1: asesorId
A2: Álvaro Pelaéz | F2: aljop84@gmail.com | G2: embajador | H2: alvaro-pelaez
A3: Ana María Peláez | F3: ana.pelaezc@gmail.com | G3: embajador | H3: ana-maria-pelaez
A4: Andres Agudelo | F4: jesus.agudelo8815@gmail.com | G4: embajador | H4: andres-agudelo
A5: Mauricio Echeverry Naranjo | E5: 3045777537 | F5: mauroverryfire1@gmail.com | G5: embajador | H5: andres-mauricio-echeverry-naranjo
A6: Andrés Mauricio Escobar Ramírez | E6: 3167447931 | F6: cvocmnty@gmail.com | G6: embajador | H6: andres-mauricio-escobar-ramirez
A7: Brenda Gómez | F7: brendiis.gomez@hotmail.com | G7: embajador | H7: brenda-gomez
A8: Carolina Molina | F8: ancamole@gmail.com | G8: embajador | H8: carolina-molina
A9: Comercial Tierra Mädre | F9: comercial.tierramadre@gmail.com | G9: embajador | H9: comercial-tierra-madre
A10: Diana Suárez | F10: dxsuarez87@gmail.com | G10: embajador | H10: diana-suarez
A11: Isa la Negra Vikinga Warrior Portocarrero | E11: 3005271933 | F11: isalavikinga@gmail.com | G11: embajador | H11: isa-la-negra-vikinga-warrior-portocarrero
A12: Jackeline Riascos Urrea | E12: 34 6432159098 | F12: jru2712@gmail.com | G12: embajador | H12: jackeline-riascos-urrea
A13: Jennyfer Florez Ocampo | E13: 3195064211 | F13: jennyferflorezcoach@gmail.com | G13: embajador | H13: jennyfer-florez-ocampo
A14: José Ignacio Florez Ricardo | F14: jflorezricardo@gmail.com | G14: embajador | H14: jose-ignacio-florez-ricardo
A15: Juan Manuel Escobar Ramirez | E15: 3041313637 | F15: juanmanuelescobarco@gmail.com | G15: embajador | H15: juan-manuel-escobar-ramirez
A16: Juan Pablo Loaiza | E16: 3042185582 | F16: bookingradial@gmail.com | G16: embajador | H16: juan-pablo-loaiza
A17: Juliana Forbes | F17: diamanteforbes@gmail.com | G17: embajador | H17: juliana-forbes
A18: Kevin Pineda Perez | E18: 3104149166 | F18: kpp.coomunity@gmail.com | G18: embajador | H18: kevin-pineda-perez
A19: Luis Alfonso Ospina Arias | E19: 3176438744 | F19: lalfonso1713@gmail.com | G19: embajador | H19: luis-alfonso-ospina-arias
A20: Mario Andres Gomez Morales | E20: 3159908888 | F20: magox.coomunity@gmail.com | G20: embajador | H20: mario-andres-gomez-morales
A21: Marsha Jauregui | F21: magnifikesmagnifik@gmail.com | G21: embajador | H21: marsha-jauregui
A22: Martiza campuzano Rodriguez | E22: 3166279999 | F22: seguimientoproduccion1@gmail.com | G22: embajador | H22: martiza-campuzano-rodriguez
A23: Mauricio Ruiz | F23: gerenciatel@gmail.com | G23: embajador | H23: mauricio-ruiz
A24: Migdalia Gomez Serna | E24: 3007669141 | F24: migdaliagomezserna553@gmail.com | G24: embajador | H24: migdalia-gomez-serna
A25: Mitchel Moreno Marin | E25: 3215274171 | F25: mitchellmorenoinvestor@gmail.com | G25: embajador | H25: mitchel-moreno-marin
A26: Olga Lucia Florez Giraldo | E26: 3104101013 | F26: olgaluciafg@gmail.com | G26: embajador | H26: olga-lucia-florez-giraldo
A27: Sebastián Pión | F27: sebastianpion@gmail.com | G27: embajador | H27: sebastian-pion
A28: Tierra Mädre | F28: tierramadre.co@gmail.com | G28: embajador | H28: tierra-madre
A29: Comunicaciones | F29: comunicaciones.tierramadre@gmail.com | G29: embajador | H29: comunicaciones
A30: Valentina Rengifo | F30: valentinarengifo8@gmail.com | G30: embajador | H30: valentina-rengifo

Sheet Ventas
A1: saleId | B1: fechaVenta | C1: itemIdsJoined | D1: clientNombre | E1: precioAcordadoCOP | F1: descuentoCOP | G1: totalCOP | H1: comisionCOP | I1: formaPago | J1: metodoContado | K1: fechaVencimiento | L1: numeroCuotas | M1: carnetUrl | N1: certificadoUrl | O1: estado
A2: VC-0001 | B2: 2026-06-03T00:01:02.912Z | C2: 140 | D2: Mitchel Moreno Marin | E2: 1500000 | F2: 420000 | G2: 1500000 | I2: contado | J2: efectivo | M2: https://drive.google.com/uc?export=view&id=1ZIz5x4B3wXvlm_hl2WtnDL6W7mhMGJrH | O2: confirmada
A3: VC-0004 | B3: 2026-07-02T05:47:51.392Z | C3: 367, 349, 87, 308, 99, 223, 346, 347, 307, 102, 127, 333, 325, 142 | D3: Álvaro Pelaéz | E3: 36587850 | F3: 0 | G3: 36587850 | I3: contado | J3: efectivo | M3: https://drive.google.com/file/d/1zfwGl7NeUgCkbb6CT8QjaRaZi9jnNJOh/view | O3: confirmada
A4: VC-0005 | B4: 2026-07-09T19:05:08.909Z | D4: Juan Pablo Loaiza | E4: 270000 | F4: 0 | G4: 270000 | I4: contado | J4: efectivo | M4: https://drive.google.com/file/d/1aUkGHZqSPBtYUd78v4ksjz3-ulWRm3jS/view | O4: confirmada

Sheet Calidades
A1: Calidad (canónica) | B1: Factor precio | C1: Nota
A2: NO OIL | B2: 1.15
A3: INSIGNIFICANT | B3: 1.2
A4: MINOR | B4: 1.1
A5: F1 | B5: 1
A6: MODERATE | B6: 0.9
A7: F2 | B7: 0.85
A8: FINA SUBLIME | B8: 0.65
A9: FINA ESENCIAL | B9: 0.55
A10: FINA | B10: 0.8
A11: FINA COMERCIAL | B11: 0.45
A12: COMERCIAL SÚPER FINA | B12: 0.4
A13: COMERCIAL FINA | B13: 0.3
... A22: Markup base (TM_MARKUP_DEFAULT) | B22: 3

Sheet Listas
A1: color | B1: calidad | C1: talla | D1: medidas | E1: categoria | F1: ubicacion | G1: estado | H1: coleccion | I1: caja | J1: procedencia | K1: tipoEsmeralda | L1: subtipoForm | M1: tipoJoya | N1: tecnicaJoya | O1: minerales | P1: complementos | Q1: formulaGema | R1: formulaJoya | S1: rangoDescuento | T1: mostrar | U1: escala16 | V1: provTipo | W1: cliTipo | X1: formaPago | Y1: metodoContado | Z1: lotEstado | AA1: saleEstado | AB1: tratamiento
A2: Verde Chivor | B2: NO OIL | C2: 0 | D2: Largo x Ancho | E2: Gema | F2: BOVEDA | G2: DISPONIBLE | H2: Centro del Universo | I2: Legalizada | J2: Boyacá | K2: Muralla | L2: Piedra | M2: Topitos Peq | N2: Engaste | O2: Platino | P2: Diamante | Q2: X1 | R2: X1 | S2: 10% | T2: Sí | U2: 1 | V2: gemas | W2: embajador | X2: contado | Y2: efectivo | Z2: abierto | AA2: reservada | AB2: Ninguno
A3: Verde Azul | B3: INSIGNIFICANT | C3: 5 | D3: Diámetro | E3: Anillo en Plata | F3: OFI.BOGOTA | G3: VENDIDA | H3: Comerciales 29-Ene | I3: Pte Legalizar | J3: Muzo | K3: Piedra Natural | L3: Gema | M3: Topitos Grandes | N3: Microengaste | O3: Oro | P3: Rubí | Q3: X1,5 | R3: X1,1 | S3: 20% | T3: No | U3: 2 | V3: joyas | W3: final | X3: credito | Y3: transferencia | Z3: cerrado | AA3: confirmada | AB3: Aceite
A4: Verde Azuloso | B4: MINOR | C4: 6 | E4: Anillo en Oro | F4: OFI.CALI | G4: ASESOR | H4: Círculos de Poder | I4: Pte Fecha x Legalizar | J4: Chivor | K4: Canutillo | L4: Lote | M4: Topitos Hombre | N4: Filigrana | O4: Oro Rosado | P4: Zafiro | Q4: X2 | R4: X1,2 | S4: 30% | T4: TRUE | U4: 3 | V4: insumos | X4: esmereogenesis | Y4: crypto | Z4: publicado | AA4: cancelada | AB4: Resina
A5: Verde Muzo | B5: F1 | C5: 7 | E5: Aretes | F5: ASESOR | G5: CONSIGNACION | H5: Dinastías | I5: Esmereogenesis | J5: Coscuez | K5: Cola | L5: Joya | M5: Aretes | N5: Fundición | O5: Oro Italiano | P5: Circones (Natural) | Q5: X2,5 | R5: X1,5 | S5: 40% | T5: FALSE | U5: 4 | V5: otros | X5: canje | Z5: cancelado | AB5: Cedar
A6: Verde Vívido | B6: MODERATE | C6: 8 | E6: Topitos | F6: EMBAJADOR | G6: Retornado | H6: Encanto de la Montaña | J6: Gachalá | K6: Raíz | L6: Lote de joyas | M6: Pulsera | N6: Cera perdida | O6: Oro Blanco | P6: Circonia | Q6: X3 | R6: X2 | S6: 50% | U6: 5 | X6: bajo_pedido | Z6: activa | AB6: Estándar
A7: Verde Intenso | B7: F2 | C7: 9 | E7: Pulsera | F7: CLIENTE | G7: ESMEREOGENESIS | H7: Finas 29-Ene | J7: Peñas Blancas | K7: Gema Facetada | L7: Ganga | M7: Dije | N7: Repujado | O7: Oro Negro | P7: Cuarzos | R7: X2,5 | S7: 60% | U7: 6 | X7: consignacion | Z7: archivada | AB7: Natural
A8: Verde Selva | B8: FINA SUBLIME | C8: Baguette | E8: Dije | F8: EN PRODUCCION | G8: ESMERO | H8: Fénix | J8: La Pita | K8: Gola | L8: Macla | M8: Cadena | N8: Calado | O8: Plata 925 | R8: X3 | S8: 70% | AB8: Perma
A9: Verde Natural | B9: FINA ESENCIAL | C9: Brillante | E9: Lote de Gemas | F9: EN CERTIFICACION | G9: DISPONIBLE ADOPTADA | H9: Madres | J9: Quípama | K9: Gola - Murralla | L9: Canutillo | M9: Expansión | N9: Martillado | O9: Plata Rodinada | AB9: Pulida
A10: Verde Limón | B10: FINA | C10: Cabuchon | E10: Joyas | F10: RETORNADO | G10: LOTE X CT | H10: Mariposas de la Montaña | J10: Maripí | K10: Mixto | L10: Insumo | M10: Anillo Mujer | N10: Granulado | O10: Plata China | AB10: Robinada
A11: Verde Viche | B11: FINA COMERCIAL | C11: Canutillo | E11: Piedras | H11: Marketing | J11: Otanche | K11: Murralla + Cristal | L11: Otros | M11: Anillo Hombre | N11: Soldadura | O11: Plata Baño de Oro | AB11: Rodinado
A12: Verde Menta | B12: COMERCIAL SÚPER FINA | C12: Chispero | E12: Dúo Gemas | H12: Princesas | J12: Pauna | K12: Piedra Cristal | L12: LOTE DE JOYAS | M12: Candonga | N12: Electroformado | O12: Bronce | AB12: Variado
A13: Verde Diamantado | B13: COMERCIAL FINA | C13: Chisperito | E13: Gema Facetada | H13: Reinas | J13: San Pablo de Borbur | M13: Set | N13: Alambrado artesanal | O13: Bronce Baño de Oro
A14: Verde Brillante | B14: COMERCIAL SUPERIOR | C14: Corazón | E14: Gemas sueltas | H14: Secretos del Bosque | J14: Yacopí | M14: Choker | N14: Rodinado | O14: Tela
A15: Verde | B15: COMERCIAL ESTÁNDAR | C15: Cuadrada | E15: Gola | H15: Sueños de Mina | J15: Cali | M15: Collar | O15: Hilos
A16: Verde Aguamarina | B16: COMERCIAL | C16: Cushion | E16: Insumo | H16: Terrícolas | J16: Chivor y Muzo | M16: Muralla
A17: Verde claro | B17: Morralla Pulida | C17: En Bruto-Natural | E17: Joya | H17: #4000 | M17: Topitos
A18: Verde Cristal | B18: Morralla Superior | C18: Esmeralda | E18: Joyería Artesanal | H18: 11:11
A19: Verde profundo | B19: Morralla Fina | C19: Gola | E19: Lote Piedras
A20: Verde Turquesa | B20: Morralla Comercial | C20: Iris | E20: Marketing
B21: 1/6 | C21: Lágrima | E21: Muralla
B22: Plata - comercial | C22: Marquis | E22: Otro
B23: Tierra Madre | C23: Marquise | E23: Piedra Cristal
B24: Variada | C24: Morralla-Lapidada | E24: Piedra Natural
C25: Ovalo | E25: Rarezas
C26: Pera | E26: Raíz
C27: Princesa
C28: Rectangular
C29: Redonda
C30: Redonda calibrada
C31: Superman
C32: Trapecio
C33: Trillion
C34: Variado
C35: Varias
C36: Ancestral
C37: Antiguo
C38: Natural
... C40: Semicuadrada
